{
  "last_updated": "2026/06/29 20:30",
  "api_cost_estimate": "本次執行約消耗 93 次 FinMind API（快取節省不計入）",
  "market_regime": {
    "regime": "多頭",
    "emoji": "🟢",
    "twii_close": 44999.9,
    "twii_ma60": 41311.01,
    "gap_pct": 8.93,
    "slope_up": true,
    "vol_threshold": 2000,
    "volratio_threshold": 1.2,
    "score_factor": 1.0,
    "rsi_ceiling": 80,
    "note": "🟢 多頭：加權 44999.9 vs MA60 41311.01（乖離 8.93%，MA60上彎）"
  },
  "dashboard_stats": {
    "industry_distribution": [
      {
        "industry": "電子零組件業",
        "count": 7
      },
      {
        "industry": "電子工業",
        "count": 6
      },
      {
        "industry": "化學生技醫療",
        "count": 3
      },
      {
        "industry": "半導體業",
        "count": 3
      },
      {
        "industry": "紡織纖維",
        "count": 2
      },
      {
        "industry": "電腦及週邊設備業",
        "count": 2
      },
      {
        "industry": "運動休閒",
        "count": 2
      },
      {
        "industry": "光電業",
        "count": 2
      },
      {
        "industry": "航運業",
        "count": 1
      },
      {
        "industry": "電機機械",
        "count": 1
      },
      {
        "industry": "汽車工業",
        "count": 1
      },
      {
        "industry": "其他電子業",
        "count": 1
      }
    ],
    "action_ratio": {
      "buy": 4,
      "watch": 30
    },
    "pool_buy_stats": {
      "🔥 姊夫爆發小魚池": {
        "total": 5,
        "buy": 1
      },
      "🍁 楓大永動魚池": {
        "total": 7,
        "buy": 0
      },
      "🌟 彼神黃金魚池": {
        "total": 6,
        "buy": 0
      },
      "🔭 測試員觀察水域": {
        "total": 14,
        "buy": 1
      },
      "🐅 三日成猛虎水池": {
        "total": 2,
        "buy": 2
      }
    },
    "ocean_total": 37
  },
  "pools": {
    "🔥 姊夫爆發小魚池": [
      {
        "stock_id": "1711",
        "stock_name": "永光",
        "industry": "化學生技醫療",
        "close": 43.6,
        "volume": 5298,
        "inst_buy": 2063,
        "foreign_buy": 1922,
        "trust_buy": 0,
        "ma5": 45.43,
        "ma30": 46.89,
        "action": "靜候觀察",
        "target_price": 65.4,
        "stop_loss": 37.84,
        "stop_loss_fixed": 39.24,
        "atr14": 2.88,
        "atr_pct": 6.61,
        "stop_loss_mode": "ATR",
        "first_target": 50.14,
        "sweet_buy_low": 44.61,
        "sweet_buy_high": 45.43,
        "theme_tag": "🔬 半導體",
        "ma10": 45.42,
        "rsi14": 48.1,
        "vol_ratio": 0.59,
        "bull_align": false,
        "chip_signal": "外資單買",
        "inst_grade": "A",
        "strength_score": 38,
        "sweet_confidence": "LOW",
        "ma5_breakout_day": 0,
        "breakout_label": "",
        "ma5_above_ma10_days": 6,
        "trend_quality": "WEAK",
        "above_ma5_streak": 0,
        "low_guard_today": false,
        "bottom_rising": false,
        "price_date": "2026-06-29"
      },
      {
        "stock_id": "4966",
        "stock_name": "譜瑞-KY",
        "industry": "半導體業",
        "close": 631.0,
        "volume": 1259,
        "inst_buy": 970,
        "foreign_buy": 3418,
        "trust_buy": -2024,
        "ma5": 644.4,
        "ma30": 731.7,
        "action": "靜候觀察",
        "target_price": 946.5,
        "stop_loss": 560.86,
        "stop_loss_fixed": 567.9,
        "atr14": 35.07,
        "atr_pct": 5.56,
        "stop_loss_mode": "ATR",
        "first_target": 725.65,
        "sweet_buy_low": 650.08,
        "sweet_buy_high": 662.0,
        "theme_tag": "🔬 半導體",
        "ma10": 662.0,
        "rsi14": 43.5,
        "vol_ratio": 0.77,
        "bull_align": false,
        "chip_signal": "外資單買",
        "inst_grade": "B",
        "strength_score": 29,
        "sweet_confidence": "LOW",
        "ma5_breakout_day": 0,
        "breakout_label": "",
        "ma5_above_ma10_days": 0,
        "trend_quality": "WEAK",
        "above_ma5_streak": 0,
        "low_guard_today": true,
        "bottom_rising": false,
        "price_date": "2026-06-29"
      },
      {
        "stock_id": "1519",
        "stock_name": "華城",
        "industry": "電機機械",
        "close": 783.0,
        "volume": 1473,
        "inst_buy": -8436,
        "foreign_buy": -7559,
        "trust_buy": -739,
        "ma5": 800.6,
        "ma30": 824.37,
        "action": "靜候觀察",
        "target_price": 1174.5,
        "stop_loss": 717.86,
        "stop_loss_fixed": 704.7,
        "atr14": 32.57,
        "atr_pct": 4.16,
        "stop_loss_mode": "ATR",
        "first_target": 900.45,
        "sweet_buy_low": 789.53,
        "sweet_buy_high": 804.0,
        "theme_tag": "🔬 半導體",
        "ma10": 804.0,
        "rsi14": 43.5,
        "vol_ratio": 0.81,
        "bull_align": false,
        "chip_signal": "無買",
        "inst_grade": "X",
        "strength_score": 12,
        "sweet_confidence": "LOW",
        "ma5_breakout_day": 0,
        "breakout_label": "",
        "ma5_above_ma10_days": 0,
        "trend_quality": "WEAK",
        "above_ma5_streak": 0,
        "low_guard_today": true,
        "bottom_rising": false,
        "price_date": "2026-06-29"
      },
      {
        "stock_id": "5312",
        "stock_name": "寶島科",
        "industry": "生技醫療業",
        "close": 87.8,
        "volume": 134,
        "inst_buy": -152,
        "foreign_buy": -154,
        "trust_buy": 0,
        "ma5": 89.54,
        "ma30": 88.88,
        "action": "靜候觀察",
        "target_price": 131.7,
        "stop_loss": 82.53,
        "stop_loss_fixed": 79.02,
        "atr14": 1.52,
        "atr_pct": 1.73,
        "stop_loss_mode": "ATR",
        "first_target": 100.97,
        "sweet_buy_low": 88.33,
        "sweet_buy_high": 89.95,
        "theme_tag": "🔬 半導體",
        "ma10": 89.95,
        "rsi14": 46.8,
        "vol_ratio": 0.89,
        "bull_align": false,
        "chip_signal": "無買",
        "inst_grade": "X",
        "strength_score": 28,
        "sweet_confidence": "LOW",
        "ma5_breakout_day": 14,
        "breakout_label": "📈 趨勢延伸（第 14 日）",
        "ma5_above_ma10_days": 0,
        "trend_quality": "WEAK",
        "above_ma5_streak": 0,
        "low_guard_today": false,
        "bottom_rising": false,
        "price_date": "2026-06-29"
      },
      {
        "stock_id": "6191",
        "stock_name": "精成科",
        "industry": "電子零組件業",
        "close": 106.0,
        "volume": 34420,
        "inst_buy": 12301,
        "foreign_buy": 5752,
        "trust_buy": 5871,
        "ma5": 100.66,
        "ma30": 97.67,
        "action": "買入加碼",
        "target_price": 159.0,
        "stop_loss": 95.72,
        "stop_loss_fixed": 95.4,
        "atr14": 5.14,
        "atr_pct": 4.85,
        "stop_loss_mode": "ATR",
        "first_target": 121.9,
        "sweet_buy_low": 100.27,
        "sweet_buy_high": 101.89,
        "theme_tag": "🔬 半導體",
        "ma10": 101.08,
        "rsi14": 64.3,
        "vol_ratio": 2.17,
        "bull_align": false,
        "chip_signal": "雙買",
        "inst_grade": "S",
        "strength_score": 100,
        "sweet_confidence": "MID",
        "ma5_breakout_day": 9,
        "breakout_label": "📈 趨勢延伸（第 9 日）",
        "ma5_above_ma10_days": 0,
        "trend_quality": "WEAK",
        "above_ma5_streak": 2,
        "low_guard_today": true,
        "bottom_rising": true,
        "price_date": "2026-06-29"
      }
    ],
    "🍁 楓大永動魚池": [
      {
        "stock_id": "2308",
        "stock_name": "台達電",
        "industry": "電子零組件業",
        "close": 1905.0,
        "volume": 16692,
        "inst_buy": -29477,
        "foreign_buy": -13075,
        "trust_buy": -13546,
        "ma5": 1955.0,
        "ma30": 2186.23,
        "action": "靜候觀察",
        "target_price": 2857.5,
        "stop_loss": 1656.38,
        "stop_loss_fixed": 1714.5,
        "atr14": 124.31,
        "atr_pct": 6.53,
        "stop_loss_mode": "ATR",
        "first_target": 2190.75,
        "sweet_buy_low": 2027.53,
        "sweet_buy_high": 2064.69,
        "theme_tag": "🔬 半導體",
        "ma10": 2064.69,
        "rsi14": 33.0,
        "vol_ratio": 0.98,
        "bull_align": false,
        "chip_signal": "無買",
        "inst_grade": "X",
        "strength_score": 16,
        "sweet_confidence": "LOW",
        "ma5_breakout_day": 0,
        "breakout_label": "",
        "ma5_above_ma10_days": 0,
        "trend_quality": "WEAK",
        "above_ma5_streak": 0,
        "low_guard_today": true,
        "bottom_rising": false,
        "price_date": "2026-06-29"
      },
      {
        "stock_id": "00923",
        "stock_name": "群益台ESG低碳50",
        "industry": "ETF",
        "close": 41.79,
        "volume": 3606,
        "inst_buy": 10198,
        "foreign_buy": 1542,
        "trust_buy": 6874,
        "ma5": 42.65,
        "ma30": 41.33,
        "action": "靜候觀察",
        "target_price": 62.69,
        "stop_loss": 39.28,
        "stop_loss_fixed": 37.61,
        "atr14": 1.2,
        "atr_pct": 2.87,
        "stop_loss_mode": "ATR",
        "first_target": 48.06,
        "sweet_buy_low": 42.54,
        "sweet_buy_high": 43.22,
        "theme_tag": "📊 ETF",
        "ma10": 42.88,
        "rsi14": 55.3,
        "vol_ratio": 0.7,
        "bull_align": false,
        "chip_signal": "雙買",
        "inst_grade": "S",
        "strength_score": 76,
        "sweet_confidence": "MID",
        "ma5_breakout_day": 29,
        "breakout_label": "📈 趨勢延伸（第 29 日）",
        "ma5_above_ma10_days": 0,
        "trend_quality": "WEAK",
        "above_ma5_streak": 0,
        "low_guard_today": true,
        "bottom_rising": false,
        "price_date": "2026-06-29"
      },
      {
        "stock_id": "00910",
        "stock_name": "第一金太空衛星",
        "industry": "ETF",
        "close": 59.25,
        "volume": 2553,
        "inst_buy": -35802,
        "foreign_buy": -10668,
        "trust_buy": 0,
        "ma5": 60.31,
        "ma30": 73.33,
        "action": "靜候觀察",
        "target_price": 88.88,
        "stop_loss": 53.71,
        "stop_loss_fixed": 53.33,
        "atr14": 2.77,
        "atr_pct": 4.68,
        "stop_loss_mode": "ATR",
        "first_target": 68.14,
        "sweet_buy_low": 62.87,
        "sweet_buy_high": 64.02,
        "theme_tag": "📊 ETF",
        "ma10": 64.02,
        "rsi14": 32.9,
        "vol_ratio": 0.58,
        "bull_align": false,
        "chip_signal": "無買",
        "inst_grade": "X",
        "strength_score": 6,
        "sweet_confidence": "LOW",
        "ma5_breakout_day": 0,
        "breakout_label": "",
        "ma5_above_ma10_days": 0,
        "trend_quality": "WEAK",
        "above_ma5_streak": 0,
        "low_guard_today": true,
        "bottom_rising": false,
        "price_date": "2026-06-29"
      },
      {
        "stock_id": "2327",
        "stock_name": "國巨*",
        "industry": "電子工業",
        "close": 1040.0,
        "volume": 40821,
        "inst_buy": -8349,
        "foreign_buy": -92926,
        "trust_buy": 82478,
        "ma5": 1050.0,
        "ma30": 816.2,
        "action": "靜候觀察",
        "target_price": 1560.0,
        "stop_loss": 884.0,
        "stop_loss_fixed": 936.0,
        "atr14": 87.57,
        "atr_pct": 8.42,
        "stop_loss_mode": "ATR",
        "first_target": 1196.0,
        "sweet_buy_low": 1041.6,
        "sweet_buy_high": 1058.4,
        "theme_tag": "🔬 半導體",
        "ma10": 1026.9,
        "rsi14": 72.7,
        "vol_ratio": 0.84,
        "bull_align": true,
        "chip_signal": "投信單買",
        "inst_grade": "X",
        "strength_score": 52,
        "sweet_confidence": "MID",
        "ma5_breakout_day": 29,
        "breakout_label": "📈 趨勢延伸（第 29 日）",
        "ma5_above_ma10_days": 12,
        "trend_quality": "WEAK",
        "above_ma5_streak": 0,
        "low_guard_today": false,
        "bottom_rising": false,
        "price_date": "2026-06-29"
      },
      {
        "stock_id": "1785",
        "stock_name": "光洋科",
        "industry": "其他電子類",
        "close": 140.5,
        "volume": 10022,
        "inst_buy": -29714,
        "foreign_buy": -27816,
        "trust_buy": -1019,
        "ma5": 142.7,
        "ma30": 143.45,
        "action": "靜候觀察",
        "target_price": 210.75,
        "stop_loss": 122.92,
        "stop_loss_fixed": 126.45,
        "atr14": 8.79,
        "atr_pct": 6.26,
        "stop_loss_mode": "ATR",
        "first_target": 161.57,
        "sweet_buy_low": 143.24,
        "sweet_buy_high": 145.56,
        "theme_tag": "🔬 半導體",
        "ma10": 144.4,
        "rsi14": 59.8,
        "vol_ratio": 0.58,
        "bull_align": false,
        "chip_signal": "無買",
        "inst_grade": "X",
        "strength_score": 25,
        "sweet_confidence": "MID",
        "ma5_breakout_day": 0,
        "breakout_label": "",
        "ma5_above_ma10_days": 0,
        "trend_quality": "WEAK",
        "above_ma5_streak": 0,
        "low_guard_today": false,
        "bottom_rising": false,
        "price_date": "2026-06-29"
      },
      {
        "stock_id": "2344",
        "stock_name": "華邦電",
        "industry": "電子工業",
        "close": 203.0,
        "volume": 149598,
        "inst_buy": 151470,
        "foreign_buy": -132479,
        "trust_buy": 291620,
        "ma5": 209.1,
        "ma30": 168.65,
        "action": "靜候觀察",
        "target_price": 304.5,
        "stop_loss": 172.78,
        "stop_loss_fixed": 182.7,
        "atr14": 15.11,
        "atr_pct": 7.44,
        "stop_loss_mode": "ATR",
        "first_target": 233.45,
        "sweet_buy_low": 207.43,
        "sweet_buy_high": 210.77,
        "theme_tag": "🔬 半導體",
        "ma10": 207.1,
        "rsi14": 68.7,
        "vol_ratio": 0.66,
        "bull_align": true,
        "chip_signal": "投信單買",
        "inst_grade": "S",
        "strength_score": 78,
        "sweet_confidence": "MID",
        "ma5_breakout_day": 29,
        "breakout_label": "📈 趨勢延伸（第 29 日）",
        "ma5_above_ma10_days": 9,
        "trend_quality": "WEAK",
        "above_ma5_streak": 0,
        "low_guard_today": false,
        "bottom_rising": false,
        "price_date": "2026-06-29"
      },
      {
        "stock_id": "6155",
        "stock_name": "鈞寶",
        "industry": "電子工業",
        "close": 84.2,
        "volume": 3999,
        "inst_buy": 777,
        "foreign_buy": 780,
        "trust_buy": 0,
        "ma5": 87.26,
        "ma30": 75.11,
        "action": "靜候觀察",
        "target_price": 126.3,
        "stop_loss": 71.57,
        "stop_loss_fixed": 75.78,
        "atr14": 7.83,
        "atr_pct": 9.3,
        "stop_loss_mode": "ATR",
        "first_target": 96.83,
        "sweet_buy_low": 89.17,
        "sweet_buy_high": 90.61,
        "theme_tag": "🔬 半導體",
        "ma10": 89.89,
        "rsi14": 55.7,
        "vol_ratio": 0.43,
        "bull_align": false,
        "chip_signal": "外資單買",
        "inst_grade": "B",
        "strength_score": 54,
        "sweet_confidence": "MID",
        "ma5_breakout_day": 29,
        "breakout_label": "📈 趨勢延伸（第 29 日）",
        "ma5_above_ma10_days": 0,
        "trend_quality": "WEAK",
        "above_ma5_streak": 0,
        "low_guard_today": false,
        "bottom_rising": false,
        "price_date": "2026-06-29"
      }
    ],
    "🌟 彼神黃金魚池": [
      {
        "stock_id": "2484",
        "stock_name": "希華",
        "industry": "電子零組件業",
        "close": 69.2,
        "volume": 63236,
        "inst_buy": 6213,
        "foreign_buy": 6087,
        "trust_buy": 0,
        "ma5": 69.64,
        "ma30": 58.54,
        "action": "靜候觀察",
        "target_price": 103.8,
        "stop_loss": 58.82,
        "stop_loss_fixed": 62.28,
        "atr14": 6.14,
        "atr_pct": 8.87,
        "stop_loss_mode": "ATR",
        "first_target": 79.58,
        "sweet_buy_low": 69.39,
        "sweet_buy_high": 70.51,
        "theme_tag": "🔬 半導體",
        "ma10": 69.95,
        "rsi14": 61.9,
        "vol_ratio": 1.64,
        "bull_align": false,
        "chip_signal": "外資單買",
        "inst_grade": "S",
        "strength_score": 80,
        "sweet_confidence": "MID",
        "ma5_breakout_day": 28,
        "breakout_label": "📈 趨勢延伸（第 28 日）",
        "ma5_above_ma10_days": 0,
        "trend_quality": "WEAK",
        "above_ma5_streak": 0,
        "low_guard_today": true,
        "bottom_rising": true,
        "price_date": "2026-06-29"
      },
      {
        "stock_id": "3221",
        "stock_name": "台嘉碩",
        "industry": "通信網路業",
        "close": 57.9,
        "volume": 13083,
        "inst_buy": -1067,
        "foreign_buy": -1378,
        "trust_buy": 0,
        "ma5": 56.68,
        "ma30": 57.12,
        "action": "靜候觀察",
        "target_price": 86.85,
        "stop_loss": 49.21,
        "stop_loss_fixed": 52.11,
        "atr14": 4.53,
        "atr_pct": 7.82,
        "stop_loss_mode": "ATR",
        "first_target": 66.58,
        "sweet_buy_low": 58.11,
        "sweet_buy_high": 59.05,
        "theme_tag": "🔬 半導體",
        "ma10": 58.58,
        "rsi14": 49.7,
        "vol_ratio": 1.45,
        "bull_align": false,
        "chip_signal": "無買",
        "inst_grade": "X",
        "strength_score": 36,
        "sweet_confidence": "MID",
        "ma5_breakout_day": 0,
        "breakout_label": "",
        "ma5_above_ma10_days": 0,
        "trend_quality": "WEAK",
        "above_ma5_streak": 2,
        "low_guard_today": false,
        "bottom_rising": false,
        "price_date": "2026-06-29"
      },
      {
        "stock_id": "8182",
        "stock_name": "加高",
        "industry": "電子零組件業",
        "close": 48.25,
        "volume": 14146,
        "inst_buy": -138,
        "foreign_buy": -80,
        "trust_buy": 0,
        "ma5": 49.32,
        "ma30": 46.67,
        "action": "靜候觀察",
        "target_price": 72.38,
        "stop_loss": 41.01,
        "stop_loss_fixed": 43.43,
        "atr14": 4.41,
        "atr_pct": 9.14,
        "stop_loss_mode": "ATR",
        "first_target": 55.49,
        "sweet_buy_low": 50.24,
        "sweet_buy_high": 51.06,
        "theme_tag": "🔬 半導體",
        "ma10": 50.65,
        "rsi14": 52.8,
        "vol_ratio": 2.19,
        "bull_align": false,
        "chip_signal": "無買",
        "inst_grade": "X",
        "strength_score": 56,
        "sweet_confidence": "MID",
        "ma5_breakout_day": 26,
        "breakout_label": "📈 趨勢延伸（第 26 日）",
        "ma5_above_ma10_days": 0,
        "trend_quality": "WEAK",
        "above_ma5_streak": 0,
        "low_guard_today": true,
        "bottom_rising": true,
        "price_date": "2026-06-29"
      },
      {
        "stock_id": "8289",
        "stock_name": "泰藝",
        "industry": "電子零組件業",
        "close": 58.4,
        "volume": 4907,
        "inst_buy": -976,
        "foreign_buy": -976,
        "trust_buy": 0,
        "ma5": 59.36,
        "ma30": 65.77,
        "action": "靜候觀察",
        "target_price": 87.6,
        "stop_loss": 49.64,
        "stop_loss_fixed": 52.56,
        "atr14": 5.11,
        "atr_pct": 8.75,
        "stop_loss_mode": "ATR",
        "first_target": 67.16,
        "sweet_buy_low": 62.91,
        "sweet_buy_high": 63.93,
        "theme_tag": "🔬 半導體",
        "ma10": 63.42,
        "rsi14": 39.5,
        "vol_ratio": 1.32,
        "bull_align": false,
        "chip_signal": "無買",
        "inst_grade": "X",
        "strength_score": 16,
        "sweet_confidence": "MID",
        "ma5_breakout_day": 0,
        "breakout_label": "",
        "ma5_above_ma10_days": 0,
        "trend_quality": "WEAK",
        "above_ma5_streak": 0,
        "low_guard_today": false,
        "bottom_rising": false,
        "price_date": "2026-06-29"
      },
      {
        "stock_id": "3042",
        "stock_name": "晶技",
        "industry": "電子工業",
        "close": 185.5,
        "volume": 16249,
        "inst_buy": -7363,
        "foreign_buy": -6413,
        "trust_buy": 1453,
        "ma5": 189.3,
        "ma30": 198.1,
        "action": "靜候觀察",
        "target_price": 278.25,
        "stop_loss": 157.67,
        "stop_loss_fixed": 166.95,
        "atr14": 18.33,
        "atr_pct": 9.88,
        "stop_loss_mode": "ATR",
        "first_target": 213.32,
        "sweet_buy_low": 201.53,
        "sweet_buy_high": 205.22,
        "theme_tag": "🔬 半導體",
        "ma10": 205.22,
        "rsi14": 42.9,
        "vol_ratio": 0.8,
        "bull_align": false,
        "chip_signal": "投信單買",
        "inst_grade": "X",
        "strength_score": 32,
        "sweet_confidence": "LOW",
        "ma5_breakout_day": 0,
        "breakout_label": "",
        "ma5_above_ma10_days": 0,
        "trend_quality": "WEAK",
        "above_ma5_streak": 0,
        "low_guard_today": false,
        "bottom_rising": false,
        "price_date": "2026-06-29"
      },
      {
        "stock_id": "3675",
        "stock_name": "德微",
        "industry": "半導體業",
        "close": 344.0,
        "volume": 500,
        "inst_buy": 1341,
        "foreign_buy": 868,
        "trust_buy": 479,
        "ma5": 389.5,
        "ma30": 347.87,
        "action": "靜候觀察",
        "target_price": 516.0,
        "stop_loss": 292.4,
        "stop_loss_fixed": 309.6,
        "atr14": 29.71,
        "atr_pct": 8.64,
        "stop_loss_mode": "ATR",
        "first_target": 395.6,
        "sweet_buy_low": 382.49,
        "sweet_buy_high": 389.5,
        "theme_tag": "🔬 半導體",
        "ma10": 369.4,
        "rsi14": 49.7,
        "vol_ratio": 0.14,
        "bull_align": true,
        "chip_signal": "雙買",
        "inst_grade": "A",
        "strength_score": 61,
        "sweet_confidence": "LOW",
        "ma5_breakout_day": 8,
        "breakout_label": "📈 趨勢延伸（第 8 日）",
        "ma5_above_ma10_days": 7,
        "trend_quality": "WEAK",
        "above_ma5_streak": 0,
        "low_guard_today": false,
        "bottom_rising": false,
        "price_date": "2026-06-29"
      }
    ],
    "🔭 測試員觀察水域": [
      {
        "stock_id": "5289",
        "stock_name": "宜鼎",
        "industry": "電腦及週邊設備業",
        "close": 1595.0,
        "volume": 3213,
        "inst_buy": -4131,
        "foreign_buy": -2967,
        "trust_buy": -929,
        "ma5": 1724.0,
        "ma30": 1799.33,
        "action": "靜候觀察",
        "target_price": 2392.5,
        "stop_loss": 1355.75,
        "stop_loss_fixed": 1435.5,
        "atr14": 131.79,
        "atr_pct": 8.26,
        "stop_loss_mode": "ATR",
        "first_target": 1834.25,
        "sweet_buy_low": 1810.4,
        "sweet_buy_high": 1839.6,
        "theme_tag": "📌 其他",
        "ma10": 1825.0,
        "rsi14": 41.7,
        "vol_ratio": 1.08,
        "bull_align": false,
        "chip_signal": "無買",
        "inst_grade": "X",
        "strength_score": 22,
        "sweet_confidence": "MID",
        "ma5_breakout_day": 0,
        "breakout_label": "",
        "ma5_above_ma10_days": 0,
        "trend_quality": "WEAK",
        "above_ma5_streak": 0,
        "low_guard_today": false,
        "bottom_rising": false,
        "price_date": "2026-06-29"
      },
      {
        "stock_id": "5292",
        "stock_name": "華懋",
        "industry": "綠能環保",
        "close": 212.0,
        "volume": 82,
        "inst_buy": -37,
        "foreign_buy": -78,
        "trust_buy": -5,
        "ma5": 216.4,
        "ma30": 220.23,
        "action": "靜候觀察",
        "target_price": 318.0,
        "stop_loss": 196.14,
        "stop_loss_fixed": 190.8,
        "atr14": 7.93,
        "atr_pct": 3.74,
        "stop_loss_mode": "ATR",
        "first_target": 243.8,
        "sweet_buy_low": 219.73,
        "sweet_buy_high": 223.27,
        "theme_tag": "🌱 綠能",
        "ma10": 221.5,
        "rsi14": 51.9,
        "vol_ratio": 0.55,
        "bull_align": false,
        "chip_signal": "無買",
        "inst_grade": "X",
        "strength_score": 15,
        "sweet_confidence": "MID",
        "ma5_breakout_day": 0,
        "breakout_label": "",
        "ma5_above_ma10_days": 0,
        "trend_quality": "WEAK",
        "above_ma5_streak": 0,
        "low_guard_today": true,
        "bottom_rising": false,
        "price_date": "2026-06-29"
      },
      {
        "stock_id": "4749",
        "stock_name": "新應材",
        "industry": "半導體業",
        "close": 866.0,
        "volume": 1521,
        "inst_buy": -7164,
        "foreign_buy": -6033,
        "trust_buy": -769,
        "ma5": 904.2,
        "ma30": 995.75,
        "action": "靜候觀察",
        "target_price": 1299.0,
        "stop_loss": 766.2,
        "stop_loss_fixed": 779.4,
        "atr14": 49.9,
        "atr_pct": 5.76,
        "stop_loss_mode": "ATR",
        "first_target": 995.9,
        "sweet_buy_low": 923.06,
        "sweet_buy_high": 937.94,
        "theme_tag": "🔬 半導體",
        "ma10": 930.5,
        "rsi14": 40.6,
        "vol_ratio": 1.25,
        "bull_align": false,
        "chip_signal": "無買",
        "inst_grade": "X",
        "strength_score": 16,
        "sweet_confidence": "MID",
        "ma5_breakout_day": 0,
        "breakout_label": "",
        "ma5_above_ma10_days": 0,
        "trend_quality": "WEAK",
        "above_ma5_streak": 0,
        "low_guard_today": false,
        "bottom_rising": false,
        "price_date": "2026-06-29"
      },
      {
        "stock_id": "6770",
        "stock_name": "力積電",
        "industry": "電子工業",
        "close": 78.9,
        "volume": 219783,
        "inst_buy": 80976,
        "foreign_buy": 63903,
        "trust_buy": 10236,
        "ma5": 80.94,
        "ma30": 73.56,
        "action": "靜候觀察",
        "target_price": 118.35,
        "stop_loss": 67.3,
        "stop_loss_fixed": 71.01,
        "atr14": 5.8,
        "atr_pct": 7.35,
        "stop_loss_mode": "ATR",
        "first_target": 90.73,
        "sweet_buy_low": 80.29,
        "sweet_buy_high": 81.59,
        "theme_tag": "🔬 半導體",
        "ma10": 77.5,
        "rsi14": 60.8,
        "vol_ratio": 0.55,
        "bull_align": true,
        "chip_signal": "雙買",
        "inst_grade": "S",
        "strength_score": 80,
        "sweet_confidence": "MID",
        "ma5_breakout_day": 7,
        "breakout_label": "✅ 突破穩固（第 7 日）",
        "ma5_above_ma10_days": 7,
        "trend_quality": "WEAK",
        "above_ma5_streak": 0,
        "low_guard_today": false,
        "bottom_rising": false,
        "price_date": "2026-06-29"
      },
      {
        "stock_id": "8299",
        "stock_name": "群聯",
        "industry": "半導體業",
        "close": 2340.0,
        "volume": 2737,
        "inst_buy": -19517,
        "foreign_buy": -11047,
        "trust_buy": -6693,
        "ma5": 2411.0,
        "ma30": 2449.67,
        "action": "靜候觀察",
        "target_price": 3510.0,
        "stop_loss": 2024.28,
        "stop_loss_fixed": 2106.0,
        "atr14": 157.86,
        "atr_pct": 6.75,
        "stop_loss_mode": "ATR",
        "first_target": 2691.0,
        "sweet_buy_low": 2399.65,
        "sweet_buy_high": 2438.35,
        "theme_tag": "🔬 半導體",
        "ma10": 2419.0,
        "rsi14": 53.5,
        "vol_ratio": 0.5,
        "bull_align": false,
        "chip_signal": "無買",
        "inst_grade": "X",
        "strength_score": 19,
        "sweet_confidence": "MID",
        "ma5_breakout_day": 0,
        "breakout_label": "",
        "ma5_above_ma10_days": 0,
        "trend_quality": "WEAK",
        "above_ma5_streak": 0,
        "low_guard_today": true,
        "bottom_rising": false,
        "price_date": "2026-06-29"
      },
      {
        "stock_id": "3673",
        "stock_name": "TPK-KY",
        "industry": "電子工業",
        "close": 76.5,
        "volume": 9250,
        "inst_buy": -21284,
        "foreign_buy": -21279,
        "trust_buy": -9,
        "ma5": 80.14,
        "ma30": 82.25,
        "action": "靜候觀察",
        "target_price": 114.75,
        "stop_loss": 65.22,
        "stop_loss_fixed": 68.85,
        "atr14": 5.64,
        "atr_pct": 7.37,
        "stop_loss_mode": "ATR",
        "first_target": 87.97,
        "sweet_buy_low": 80.55,
        "sweet_buy_high": 82.03,
        "theme_tag": "🔬 半導體",
        "ma10": 82.03,
        "rsi14": 42.1,
        "vol_ratio": 0.57,
        "bull_align": false,
        "chip_signal": "無買",
        "inst_grade": "X",
        "strength_score": 16,
        "sweet_confidence": "LOW",
        "ma5_breakout_day": 0,
        "breakout_label": "",
        "ma5_above_ma10_days": 0,
        "trend_quality": "WEAK",
        "above_ma5_streak": 0,
        "low_guard_today": false,
        "bottom_rising": false,
        "price_date": "2026-06-29"
      },
      {
        "stock_id": "5425",
        "stock_name": "台半",
        "industry": "半導體業",
        "close": 110.0,
        "volume": 5662,
        "inst_buy": 4852,
        "foreign_buy": 2269,
        "trust_buy": 1130,
        "ma5": 123.6,
        "ma30": 103.69,
        "action": "靜候觀察",
        "target_price": 165.0,
        "stop_loss": 93.5,
        "stop_loss_fixed": 99.0,
        "atr14": 9.41,
        "atr_pct": 8.55,
        "stop_loss_mode": "ATR",
        "first_target": 126.5,
        "sweet_buy_low": 122.61,
        "sweet_buy_high": 124.59,
        "theme_tag": "🔬 半導體",
        "ma10": 117.38,
        "rsi14": 61.5,
        "vol_ratio": 0.13,
        "bull_align": true,
        "chip_signal": "雙買",
        "inst_grade": "A",
        "strength_score": 76,
        "sweet_confidence": "MID",
        "ma5_breakout_day": 29,
        "breakout_label": "📈 趨勢延伸（第 29 日）",
        "ma5_above_ma10_days": 8,
        "trend_quality": "WEAK",
        "above_ma5_streak": 0,
        "low_guard_today": false,
        "bottom_rising": false,
        "price_date": "2026-06-29"
      },
      {
        "stock_id": "6224",
        "stock_name": "聚鼎",
        "industry": "電子工業",
        "close": 70.2,
        "volume": 1048,
        "inst_buy": 48,
        "foreign_buy": 43,
        "trust_buy": 0,
        "ma5": 76.56,
        "ma30": 80.75,
        "action": "靜候觀察",
        "target_price": 105.3,
        "stop_loss": 59.67,
        "stop_loss_fixed": 63.18,
        "atr14": 5.59,
        "atr_pct": 7.96,
        "stop_loss_mode": "ATR",
        "first_target": 80.73,
        "sweet_buy_low": 77.8,
        "sweet_buy_high": 79.06,
        "theme_tag": "🔬 半導體",
        "ma10": 78.43,
        "rsi14": 43.5,
        "vol_ratio": 1.14,
        "bull_align": false,
        "chip_signal": "外資單買",
        "inst_grade": "C",
        "strength_score": 28,
        "sweet_confidence": "MID",
        "ma5_breakout_day": 0,
        "breakout_label": "",
        "ma5_above_ma10_days": 0,
        "trend_quality": "WEAK",
        "above_ma5_streak": 0,
        "low_guard_today": false,
        "bottom_rising": false,
        "price_date": "2026-06-29"
      },
      {
        "stock_id": "3707",
        "stock_name": "漢磊",
        "industry": "半導體業",
        "close": 79.0,
        "volume": 15631,
        "inst_buy": -9551,
        "foreign_buy": -9290,
        "trust_buy": 0,
        "ma5": 87.48,
        "ma30": 81.55,
        "action": "靜候觀察",
        "target_price": 118.5,
        "stop_loss": 67.15,
        "stop_loss_fixed": 71.1,
        "atr14": 6.39,
        "atr_pct": 8.09,
        "stop_loss_mode": "ATR",
        "first_target": 90.85,
        "sweet_buy_low": 86.78,
        "sweet_buy_high": 88.18,
        "theme_tag": "🔬 半導體",
        "ma10": 85.4,
        "rsi14": 56.8,
        "vol_ratio": 0.54,
        "bull_align": true,
        "chip_signal": "無買",
        "inst_grade": "X",
        "strength_score": 45,
        "sweet_confidence": "MID",
        "ma5_breakout_day": 7,
        "breakout_label": "✅ 突破穩固（第 7 日）",
        "ma5_above_ma10_days": 9,
        "trend_quality": "WEAK",
        "above_ma5_streak": 0,
        "low_guard_today": false,
        "bottom_rising": false,
        "price_date": "2026-06-29"
      },
      {
        "stock_id": "3016",
        "stock_name": "嘉晶",
        "industry": "電子工業",
        "close": 121.5,
        "volume": 5194,
        "inst_buy": 5957,
        "foreign_buy": 6419,
        "trust_buy": 0,
        "ma5": 133.46,
        "ma30": 120.53,
        "action": "靜候觀察",
        "target_price": 182.25,
        "stop_loss": 103.27,
        "stop_loss_fixed": 109.35,
        "atr14": 11.51,
        "atr_pct": 9.47,
        "stop_loss_mode": "ATR",
        "first_target": 139.72,
        "sweet_buy_low": 132.39,
        "sweet_buy_high": 134.53,
        "theme_tag": "🔬 半導體",
        "ma10": 129.73,
        "rsi14": 58.3,
        "vol_ratio": 0.49,
        "bull_align": true,
        "chip_signal": "外資單買",
        "inst_grade": "S",
        "strength_score": 70,
        "sweet_confidence": "MID",
        "ma5_breakout_day": 7,
        "breakout_label": "✅ 突破穩固（第 7 日）",
        "ma5_above_ma10_days": 10,
        "trend_quality": "WEAK",
        "above_ma5_streak": 0,
        "low_guard_today": false,
        "bottom_rising": false,
        "price_date": "2026-06-29"
      },
      {
        "stock_id": "5274",
        "stock_name": "信驊",
        "industry": "半導體業",
        "close": 15210.0,
        "volume": 409,
        "inst_buy": 89,
        "foreign_buy": 757,
        "trust_buy": -666,
        "ma5": 16966.18,
        "ma30": 17530.88,
        "action": "靜候觀察",
        "target_price": 22815.0,
        "stop_loss": 13105.12,
        "stop_loss_fixed": 13689.0,
        "atr14": 1052.44,
        "atr_pct": 6.92,
        "stop_loss_mode": "ATR",
        "first_target": 17491.5,
        "sweet_buy_low": 17567.37,
        "sweet_buy_high": 17850.71,
        "theme_tag": "🔬 半導體",
        "ma10": 17709.04,
        "rsi14": 37.6,
        "vol_ratio": 1.4,
        "bull_align": false,
        "chip_signal": "外資單買",
        "inst_grade": "C",
        "strength_score": 22,
        "sweet_confidence": "MID",
        "ma5_breakout_day": 0,
        "breakout_label": "",
        "ma5_above_ma10_days": 0,
        "trend_quality": "WEAK",
        "above_ma5_streak": 0,
        "low_guard_today": false,
        "bottom_rising": false,
        "price_date": "2026-06-29"
      },
      {
        "stock_id": "6270",
        "stock_name": "倍微",
        "industry": "電子通路業",
        "close": 39.0,
        "volume": 4426,
        "inst_buy": 666,
        "foreign_buy": 665,
        "trust_buy": 0,
        "ma5": 40.24,
        "ma30": 32.61,
        "action": "靜候觀察",
        "target_price": 58.5,
        "stop_loss": 33.15,
        "stop_loss_fixed": 35.1,
        "atr14": 3.14,
        "atr_pct": 8.05,
        "stop_loss_mode": "ATR",
        "first_target": 44.85,
        "sweet_buy_low": 39.92,
        "sweet_buy_high": 40.56,
        "theme_tag": "🔬 半導體",
        "ma10": 37.99,
        "rsi14": 56.7,
        "vol_ratio": 0.65,
        "bull_align": true,
        "chip_signal": "外資單買",
        "inst_grade": "B",
        "strength_score": 61,
        "sweet_confidence": "MID",
        "ma5_breakout_day": 24,
        "breakout_label": "📈 趨勢延伸（第 24 日）",
        "ma5_above_ma10_days": 5,
        "trend_quality": "WEAK",
        "above_ma5_streak": 0,
        "low_guard_today": false,
        "bottom_rising": false,
        "price_date": "2026-06-29"
      },
      {
        "stock_id": "6667",
        "stock_name": "信紘科",
        "industry": "其他電子類",
        "close": 260.5,
        "volume": 297,
        "inst_buy": -195,
        "foreign_buy": -254,
        "trust_buy": 0,
        "ma5": 267.5,
        "ma30": 259.57,
        "action": "靜候觀察",
        "target_price": 390.75,
        "stop_loss": 242.84,
        "stop_loss_fixed": 234.45,
        "atr14": 8.83,
        "atr_pct": 3.39,
        "stop_loss_mode": "ATR",
        "first_target": 299.57,
        "sweet_buy_low": 263.69,
        "sweet_buy_high": 268.52,
        "theme_tag": "📌 其他",
        "ma10": 268.52,
        "rsi14": 49.9,
        "vol_ratio": 0.52,
        "bull_align": false,
        "chip_signal": "無買",
        "inst_grade": "X",
        "strength_score": 24,
        "sweet_confidence": "LOW",
        "ma5_breakout_day": 21,
        "breakout_label": "📈 趨勢延伸（第 21 日）",
        "ma5_above_ma10_days": 0,
        "trend_quality": "WEAK",
        "above_ma5_streak": 0,
        "low_guard_today": true,
        "bottom_rising": false,
        "price_date": "2026-06-29"
      },
      {
        "stock_id": "3706",
        "stock_name": "神達",
        "industry": "電腦及週邊設備業",
        "close": 86.4,
        "volume": 32023,
        "inst_buy": 15871,
        "foreign_buy": -9502,
        "trust_buy": 25926,
        "ma5": 85.52,
        "ma30": 87.16,
        "action": "買入加碼",
        "target_price": 129.6,
        "stop_loss": 79.76,
        "stop_loss_fixed": 77.76,
        "atr14": 3.32,
        "atr_pct": 3.84,
        "stop_loss_mode": "ATR",
        "first_target": 99.36,
        "sweet_buy_low": 85.12,
        "sweet_buy_high": 86.5,
        "theme_tag": "📌 其他",
        "ma10": 85.81,
        "rsi14": 48.2,
        "vol_ratio": 1.92,
        "bull_align": false,
        "chip_signal": "投信單買",
        "inst_grade": "S",
        "strength_score": 67,
        "sweet_confidence": "MID",
        "ma5_breakout_day": 0,
        "breakout_label": "",
        "ma5_above_ma10_days": 0,
        "trend_quality": "WEAK",
        "above_ma5_streak": 1,
        "low_guard_today": true,
        "bottom_rising": false,
        "price_date": "2026-06-29"
      }
    ],
    "🐅 三日成猛虎水池": [
      {
        "stock_id": "6139",
        "stock_name": "亞翔",
        "industry": "電子工業",
        "close": 955.0,
        "volume": 10224,
        "inst_buy": 6952,
        "foreign_buy": 2458,
        "trust_buy": 5588,
        "ma5": 863.4,
        "ma30": 796.4,
        "action": "買入加碼",
        "target_price": 1432.5,
        "stop_loss": 839.72,
        "stop_loss_fixed": 859.5,
        "atr14": 57.64,
        "atr_pct": 6.04,
        "stop_loss_mode": "ATR",
        "first_target": 1098.25,
        "sweet_buy_low": 856.49,
        "sweet_buy_high": 870.31,
        "theme_tag": "📌 其他",
        "ma10": 845.3,
        "rsi14": 73.5,
        "vol_ratio": 1.54,
        "bull_align": true,
        "chip_signal": "雙買",
        "inst_grade": "S",
        "strength_score": 98,
        "sweet_confidence": "MID",
        "ma5_breakout_day": 29,
        "breakout_label": "📈 趨勢延伸（第 29 日）",
        "ma5_above_ma10_days": 10,
        "trend_quality": "WATCH",
        "above_ma5_streak": 4,
        "low_guard_today": true,
        "bottom_rising": true,
        "price_date": "2026-06-29"
      },
      {
        "stock_id": "2404",
        "stock_name": "漢唐",
        "industry": "電子工業",
        "close": 1360.0,
        "volume": 4703,
        "inst_buy": 12294,
        "foreign_buy": 18108,
        "trust_buy": -5492,
        "ma5": 1316.0,
        "ma30": 1209.17,
        "action": "買入加碼",
        "target_price": 2040.0,
        "stop_loss": 1185.0,
        "stop_loss_fixed": 1224.0,
        "atr14": 87.5,
        "atr_pct": 6.43,
        "stop_loss_mode": "ATR",
        "first_target": 1564.0,
        "sweet_buy_low": 1305.47,
        "sweet_buy_high": 1326.53,
        "theme_tag": "📌 其他",
        "ma10": 1303.0,
        "rsi14": 67.1,
        "vol_ratio": 1.27,
        "bull_align": true,
        "chip_signal": "外資單買",
        "inst_grade": "S",
        "strength_score": 92,
        "sweet_confidence": "MID",
        "ma5_breakout_day": 29,
        "breakout_label": "📈 趨勢延伸（第 29 日）",
        "ma5_above_ma10_days": 11,
        "trend_quality": "WATCH",
        "above_ma5_streak": 3,
        "low_guard_today": true,
        "bottom_rising": true,
        "price_date": "2026-06-29"
      }
    ],
    "🃏 被動卡娃魚池": [
      {
        "stock_id": "6173",
        "stock_name": "信昌電",
        "industry": "電子零組件業",
        "close": 282.5,
        "volume": 908,
        "inst_buy": -657,
        "foreign_buy": -1836,
        "trust_buy": 1980,
        "ma5": 291.0,
        "ma30": 242.47,
        "action": "靜候觀察",
        "target_price": 423.75,
        "stop_loss": 240.12,
        "stop_loss_fixed": 254.25,
        "atr14": 24.11,
        "atr_pct": 8.53,
        "stop_loss_mode": "ATR",
        "first_target": 324.88,
        "sweet_buy_low": 294.43,
        "sweet_buy_high": 299.17,
        "theme_tag": "📌 其他",
        "ma10": 296.8,
        "rsi14": 65.7,
        "vol_ratio": 0.78,
        "bull_align": false,
        "chip_signal": "投信單買",
        "inst_grade": "X",
        "strength_score": 45,
        "sweet_confidence": "MID",
        "ma5_breakout_day": 29,
        "breakout_label": "📈 趨勢延伸（第 29 日）",
        "ma5_above_ma10_days": 0,
        "trend_quality": "WEAK",
        "above_ma5_streak": 0,
        "low_guard_today": false,
        "bottom_rising": false,
        "price_date": "2026-06-29",
        "tier": "Tier 1"
      },
      {
        "stock_id": "3026",
        "stock_name": "禾伸堂",
        "industry": "電子零組件業",
        "close": 766.0,
        "volume": 1033,
        "inst_buy": 8530,
        "foreign_buy": 3249,
        "trust_buy": 5898,
        "ma5": 774.0,
        "ma30": 655.75,
        "action": "靜候觀察",
        "target_price": 1149.0,
        "stop_loss": 651.1,
        "stop_loss_fixed": 689.4,
        "atr14": 70.98,
        "atr_pct": 9.27,
        "stop_loss_mode": "ATR",
        "first_target": 880.9,
        "sweet_buy_low": 813.22,
        "sweet_buy_high": 826.34,
        "theme_tag": "📌 其他",
        "ma10": 819.78,
        "rsi14": 64.3,
        "vol_ratio": 0.52,
        "bull_align": false,
        "chip_signal": "雙買",
        "inst_grade": "S",
        "strength_score": 66,
        "sweet_confidence": "MID",
        "ma5_breakout_day": 29,
        "breakout_label": "📈 趨勢延伸（第 29 日）",
        "ma5_above_ma10_days": 0,
        "trend_quality": "WEAK",
        "above_ma5_streak": 0,
        "low_guard_today": true,
        "bottom_rising": false,
        "price_date": "2026-06-29",
        "tier": "Tier 1"
      },
      {
        "stock_id": "2492",
        "stock_name": "華新科",
        "industry": "電子零組件業",
        "close": 514.0,
        "volume": 4232,
        "inst_buy": 32268,
        "foreign_buy": 14013,
        "trust_buy": 18380,
        "ma5": 564.0,
        "ma30": 423.12,
        "action": "靜候觀察",
        "target_price": 771.0,
        "stop_loss": 436.9,
        "stop_loss_fixed": 462.6,
        "atr14": 53.57,
        "atr_pct": 10.42,
        "stop_loss_mode": "ATR",
        "first_target": 591.1,
        "sweet_buy_low": 559.49,
        "sweet_buy_high": 568.51,
        "theme_tag": "📌 其他",
        "ma10": 548.35,
        "rsi14": 62.8,
        "vol_ratio": 0.42,
        "bull_align": true,
        "chip_signal": "雙買",
        "inst_grade": "S",
        "strength_score": 79,
        "sweet_confidence": "MID",
        "ma5_breakout_day": 29,
        "breakout_label": "📈 趨勢延伸（第 29 日）",
        "ma5_above_ma10_days": 10,
        "trend_quality": "WEAK",
        "above_ma5_streak": 0,
        "low_guard_today": false,
        "bottom_rising": false,
        "price_date": "2026-06-29",
        "tier": "Tier 1"
      },
      {
        "stock_id": "6175",
        "stock_name": "立敦",
        "industry": "電子零組件業",
        "close": 106.0,
        "volume": 8092,
        "inst_buy": -397,
        "foreign_buy": -619,
        "trust_buy": 1,
        "ma5": 111.9,
        "ma30": 99.03,
        "action": "靜候觀察",
        "target_price": 159.0,
        "stop_loss": 90.1,
        "stop_loss_fixed": 95.4,
        "atr14": 9.5,
        "atr_pct": 8.96,
        "stop_loss_mode": "ATR",
        "first_target": 121.9,
        "sweet_buy_low": 111.0,
        "sweet_buy_high": 112.8,
        "theme_tag": "📌 其他",
        "ma10": 109.61,
        "rsi14": 53.8,
        "vol_ratio": 0.63,
        "bull_align": true,
        "chip_signal": "投信單買",
        "inst_grade": "X",
        "strength_score": 56,
        "sweet_confidence": "MID",
        "ma5_breakout_day": 29,
        "breakout_label": "📈 趨勢延伸（第 29 日）",
        "ma5_above_ma10_days": 12,
        "trend_quality": "WEAK",
        "above_ma5_streak": 0,
        "low_guard_today": false,
        "bottom_rising": false,
        "price_date": "2026-06-29",
        "tier": "Tier 2"
      },
      {
        "stock_id": "2472",
        "stock_name": "立隆電",
        "industry": "電子零組件業",
        "close": 412.5,
        "volume": 17271,
        "inst_buy": 3330,
        "foreign_buy": -3403,
        "trust_buy": 6516,
        "ma5": 381.9,
        "ma30": 344.37,
        "action": "買入加碼",
        "target_price": 618.75,
        "stop_loss": 350.62,
        "stop_loss_fixed": 371.25,
        "atr14": 38.21,
        "atr_pct": 9.26,
        "stop_loss_mode": "ATR",
        "first_target": 474.37,
        "sweet_buy_low": 378.84,
        "sweet_buy_high": 384.96,
        "theme_tag": "📌 其他",
        "ma10": 380.4,
        "rsi14": 60.5,
        "vol_ratio": 1.34,
        "bull_align": true,
        "chip_signal": "投信單買",
        "inst_grade": "A",
        "strength_score": 91,
        "sweet_confidence": "MID",
        "ma5_breakout_day": 29,
        "breakout_label": "📈 趨勢延伸（第 29 日）",
        "ma5_above_ma10_days": 10,
        "trend_quality": "WEAK",
        "above_ma5_streak": 1,
        "low_guard_today": false,
        "bottom_rising": false,
        "price_date": "2026-06-29",
        "tier": "Tier 2"
      },
      {
        "stock_id": "2327",
        "stock_name": "國巨*",
        "industry": "電子工業",
        "close": 1040.0,
        "volume": 40821,
        "inst_buy": -8349,
        "foreign_buy": -92926,
        "trust_buy": 82478,
        "ma5": 1050.0,
        "ma30": 816.2,
        "action": "靜候觀察",
        "target_price": 1560.0,
        "stop_loss": 884.0,
        "stop_loss_fixed": 936.0,
        "atr14": 87.57,
        "atr_pct": 8.42,
        "stop_loss_mode": "ATR",
        "first_target": 1196.0,
        "sweet_buy_low": 1041.6,
        "sweet_buy_high": 1058.4,
        "theme_tag": "🔬 半導體",
        "ma10": 1026.9,
        "rsi14": 72.7,
        "vol_ratio": 0.84,
        "bull_align": true,
        "chip_signal": "投信單買",
        "inst_grade": "X",
        "strength_score": 52,
        "sweet_confidence": "MID",
        "ma5_breakout_day": 29,
        "breakout_label": "📈 趨勢延伸（第 29 日）",
        "ma5_above_ma10_days": 12,
        "trend_quality": "WEAK",
        "above_ma5_streak": 0,
        "low_guard_today": false,
        "bottom_rising": false,
        "price_date": "2026-06-29",
        "tier": "Tier 2"
      },
      {
        "stock_id": "2375",
        "stock_name": "凱美",
        "industry": "電子零組件業",
        "close": 192.5,
        "volume": 11294,
        "inst_buy": -559,
        "foreign_buy": -97,
        "trust_buy": -1,
        "ma5": 202.8,
        "ma30": 164.42,
        "action": "靜候觀察",
        "target_price": 288.75,
        "stop_loss": 163.62,
        "stop_loss_fixed": 173.25,
        "atr14": 18.21,
        "atr_pct": 9.46,
        "stop_loss_mode": "ATR",
        "first_target": 221.37,
        "sweet_buy_low": 201.18,
        "sweet_buy_high": 204.42,
        "theme_tag": "📌 其他",
        "ma10": 202.25,
        "rsi14": 64.4,
        "vol_ratio": 0.67,
        "bull_align": true,
        "chip_signal": "無買",
        "inst_grade": "X",
        "strength_score": 48,
        "sweet_confidence": "MID",
        "ma5_breakout_day": 29,
        "breakout_label": "📈 趨勢延伸（第 29 日）",
        "ma5_above_ma10_days": 11,
        "trend_quality": "WEAK",
        "above_ma5_streak": 0,
        "low_guard_today": false,
        "bottom_rising": false,
        "price_date": "2026-06-29",
        "tier": "Tier 2"
      },
      {
        "stock_id": "6449",
        "stock_name": "鈺邦",
        "industry": "電子工業",
        "close": 338.0,
        "volume": 1292,
        "inst_buy": 1815,
        "foreign_buy": 1702,
        "trust_buy": 379,
        "ma5": 361.4,
        "ma30": 363.5,
        "action": "靜候觀察",
        "target_price": 507.0,
        "stop_loss": 287.3,
        "stop_loss_fixed": 304.2,
        "atr14": 42.17,
        "atr_pct": 12.48,
        "stop_loss_mode": "ATR",
        "first_target": 388.7,
        "sweet_buy_low": 394.17,
        "sweet_buy_high": 400.53,
        "theme_tag": "📌 其他",
        "ma10": 397.35,
        "rsi14": 50.7,
        "vol_ratio": 0.57,
        "bull_align": false,
        "chip_signal": "雙買",
        "inst_grade": "A",
        "strength_score": 45,
        "sweet_confidence": "MID",
        "ma5_breakout_day": 0,
        "breakout_label": "",
        "ma5_above_ma10_days": 0,
        "trend_quality": "WEAK",
        "above_ma5_streak": 0,
        "low_guard_today": false,
        "bottom_rising": false,
        "price_date": "2026-06-29",
        "tier": "Tier 2"
      },
      {
        "stock_id": "8042",
        "stock_name": "金山電",
        "industry": "電子零組件業",
        "close": 169.0,
        "volume": 852,
        "inst_buy": -4942,
        "foreign_buy": -4875,
        "trust_buy": 0,
        "ma5": 183.9,
        "ma30": 156.96,
        "action": "靜候觀察",
        "target_price": 253.5,
        "stop_loss": 143.65,
        "stop_loss_fixed": 152.1,
        "atr14": 16.32,
        "atr_pct": 9.66,
        "stop_loss_mode": "ATR",
        "first_target": 194.35,
        "sweet_buy_low": 186.55,
        "sweet_buy_high": 189.55,
        "theme_tag": "📌 其他",
        "ma10": 188.05,
        "rsi14": 63.4,
        "vol_ratio": 0.8,
        "bull_align": false,
        "chip_signal": "無買",
        "inst_grade": "X",
        "strength_score": 35,
        "sweet_confidence": "MID",
        "ma5_breakout_day": 29,
        "breakout_label": "📈 趨勢延伸（第 29 日）",
        "ma5_above_ma10_days": 0,
        "trend_quality": "WEAK",
        "above_ma5_streak": 0,
        "low_guard_today": false,
        "bottom_rising": false,
        "price_date": "2026-06-29",
        "tier": "Tier 2"
      },
      {
        "stock_id": "8163",
        "stock_name": "達方",
        "industry": "電子工業",
        "close": 39.4,
        "volume": 2369,
        "inst_buy": 9563,
        "foreign_buy": 9683,
        "trust_buy": 0,
        "ma5": 41.88,
        "ma30": 39.76,
        "action": "靜候觀察",
        "target_price": 59.1,
        "stop_loss": 33.82,
        "stop_loss_fixed": 35.46,
        "atr14": 2.79,
        "atr_pct": 7.08,
        "stop_loss_mode": "ATR",
        "first_target": 45.31,
        "sweet_buy_low": 42.82,
        "sweet_buy_high": 43.52,
        "theme_tag": "📌 其他",
        "ma10": 43.17,
        "rsi14": 52.1,
        "vol_ratio": 0.89,
        "bull_align": false,
        "chip_signal": "外資單買",
        "inst_grade": "S",
        "strength_score": 66,
        "sweet_confidence": "MID",
        "ma5_breakout_day": 29,
        "breakout_label": "📈 趨勢延伸（第 29 日）",
        "ma5_above_ma10_days": 0,
        "trend_quality": "WEAK",
        "above_ma5_streak": 0,
        "low_guard_today": false,
        "bottom_rising": false,
        "price_date": "2026-06-29",
        "tier": "Tier 2"
      },
      {
        "stock_id": "3090",
        "stock_name": "日電貿",
        "industry": "電子零組件業",
        "close": 304.0,
        "volume": 904,
        "inst_buy": 24575,
        "foreign_buy": 1547,
        "trust_buy": 23651,
        "ma5": 308.1,
        "ma30": 245.15,
        "action": "靜候觀察",
        "target_price": 456.0,
        "stop_loss": 258.4,
        "stop_loss_fixed": 273.6,
        "atr14": 26.89,
        "atr_pct": 8.85,
        "stop_loss_mode": "ATR",
        "first_target": 349.6,
        "sweet_buy_low": 305.64,
        "sweet_buy_high": 310.56,
        "theme_tag": "📌 其他",
        "ma10": 306.75,
        "rsi14": 69.4,
        "vol_ratio": 0.56,
        "bull_align": true,
        "chip_signal": "雙買",
        "inst_grade": "S",
        "strength_score": 73,
        "sweet_confidence": "MID",
        "ma5_breakout_day": 29,
        "breakout_label": "📈 趨勢延伸（第 29 日）",
        "ma5_above_ma10_days": 11,
        "trend_quality": "WEAK",
        "above_ma5_streak": 0,
        "low_guard_today": true,
        "bottom_rising": false,
        "price_date": "2026-06-29",
        "tier": "Tier 3"
      },
      {
        "stock_id": "3537",
        "stock_name": "堡達",
        "industry": "電子零組件業",
        "close": 74.7,
        "volume": 1594,
        "inst_buy": -1093,
        "foreign_buy": -1093,
        "trust_buy": 0,
        "ma5": 78.22,
        "ma30": 75.14,
        "action": "靜候觀察",
        "target_price": 112.05,
        "stop_loss": 63.49,
        "stop_loss_fixed": 67.23,
        "atr14": 6.71,
        "atr_pct": 8.98,
        "stop_loss_mode": "ATR",
        "first_target": 85.91,
        "sweet_buy_low": 78.89,
        "sweet_buy_high": 80.34,
        "theme_tag": "📌 其他",
        "ma10": 80.34,
        "rsi14": 47.8,
        "vol_ratio": 0.55,
        "bull_align": false,
        "chip_signal": "無買",
        "inst_grade": "X",
        "strength_score": 24,
        "sweet_confidence": "LOW",
        "ma5_breakout_day": 29,
        "breakout_label": "📈 趨勢延伸（第 29 日）",
        "ma5_above_ma10_days": 0,
        "trend_quality": "WEAK",
        "above_ma5_streak": 0,
        "low_guard_today": false,
        "bottom_rising": false,
        "price_date": "2026-06-29",
        "tier": "Tier 3"
      },
      {
        "stock_id": "6432",
        "stock_name": "今展科",
        "industry": "電子零組件業",
        "close": 70.2,
        "volume": 2462,
        "inst_buy": -264,
        "foreign_buy": 28,
        "trust_buy": 0,
        "ma5": 75.28,
        "ma30": 68.07,
        "action": "靜候觀察",
        "target_price": 105.3,
        "stop_loss": 59.67,
        "stop_loss_fixed": 63.18,
        "atr14": 6.95,
        "atr_pct": 9.9,
        "stop_loss_mode": "ATR",
        "first_target": 80.73,
        "sweet_buy_low": 76.34,
        "sweet_buy_high": 77.58,
        "theme_tag": "📌 其他",
        "ma10": 76.96,
        "rsi14": 53.5,
        "vol_ratio": 0.7,
        "bull_align": false,
        "chip_signal": "外資單買",
        "inst_grade": "X",
        "strength_score": 46,
        "sweet_confidence": "MID",
        "ma5_breakout_day": 29,
        "breakout_label": "📈 趨勢延伸（第 29 日）",
        "ma5_above_ma10_days": 0,
        "trend_quality": "WEAK",
        "above_ma5_streak": 0,
        "low_guard_today": false,
        "bottom_rising": false,
        "price_date": "2026-06-29",
        "tier": "Tier 3"
      }
    ],
    "🌊 汪洋大魚": [
      {
        "stock_id": "6191",
        "stock_name": "精成科",
        "industry": "電子零組件業",
        "close": 106.0,
        "volume": 34420,
        "inst_buy": 12301,
        "foreign_buy": 5752,
        "trust_buy": 5871,
        "ma5": 100.66,
        "ma30": 97.67,
        "action": "買入加碼",
        "target_price": 159.0,
        "stop_loss": 95.72,
        "stop_loss_fixed": 95.4,
        "atr14": 5.14,
        "atr_pct": 4.85,
        "stop_loss_mode": "ATR",
        "first_target": 121.9,
        "sweet_buy_low": 100.27,
        "sweet_buy_high": 101.89,
        "theme_tag": "🔬 半導體",
        "ma10": 101.08,
        "rsi14": 64.3,
        "vol_ratio": 2.17,
        "bull_align": false,
        "chip_signal": "雙買",
        "inst_grade": "S",
        "strength_score": 100,
        "sweet_confidence": "MID",
        "ma5_breakout_day": 9,
        "breakout_label": "📈 趨勢延伸（第 9 日）",
        "ma5_above_ma10_days": 0,
        "trend_quality": "WEAK",
        "above_ma5_streak": 2,
        "low_guard_today": true,
        "bottom_rising": true,
        "price_date": "2026-06-29"
      },
      {
        "stock_id": "1710",
        "stock_name": "東聯",
        "industry": "化學生技醫療",
        "close": 15.25,
        "volume": 15187,
        "inst_buy": 12591,
        "foreign_buy": 12430,
        "trust_buy": -591,
        "ma5": 14.12,
        "ma30": 13.79,
        "action": "買入加碼",
        "target_price": 22.88,
        "stop_loss": 13.97,
        "stop_loss_fixed": 13.72,
        "atr14": 0.64,
        "atr_pct": 4.2,
        "stop_loss_mode": "ATR",
        "first_target": 17.54,
        "sweet_buy_low": 14.01,
        "sweet_buy_high": 14.23,
        "theme_tag": "💊 生技醫療",
        "ma10": 13.93,
        "rsi14": 55.6,
        "vol_ratio": 2.0,
        "bull_align": true,
        "chip_signal": "外資單買",
        "inst_grade": "S",
        "strength_score": 100,
        "sweet_confidence": "HIGH",
        "ma5_breakout_day": 24,
        "breakout_label": "📈 趨勢延伸（第 24 日）",
        "ma5_above_ma10_days": 4,
        "trend_quality": "WATCH",
        "above_ma5_streak": 4,
        "low_guard_today": true,
        "bottom_rising": false,
        "price_date": "2026-06-29"
      },
      {
        "stock_id": "1447",
        "stock_name": "力鵬",
        "industry": "紡織纖維",
        "close": 6.84,
        "volume": 4880,
        "inst_buy": 1959,
        "foreign_buy": 1958,
        "trust_buy": 0,
        "ma5": 6.29,
        "ma30": 6.16,
        "action": "買入加碼",
        "target_price": 10.26,
        "stop_loss": 6.4,
        "stop_loss_fixed": 6.16,
        "atr14": 0.22,
        "atr_pct": 3.22,
        "stop_loss_mode": "ATR",
        "first_target": 7.87,
        "sweet_buy_low": 6.24,
        "sweet_buy_high": 6.34,
        "theme_tag": "📌 其他",
        "ma10": 6.19,
        "rsi14": 52.5,
        "vol_ratio": 2.15,
        "bull_align": true,
        "chip_signal": "外資單買",
        "inst_grade": "A",
        "strength_score": 99,
        "sweet_confidence": "HIGH",
        "ma5_breakout_day": 29,
        "breakout_label": "📈 趨勢延伸（第 29 日）",
        "ma5_above_ma10_days": 2,
        "trend_quality": "HEALTHY",
        "above_ma5_streak": 5,
        "low_guard_today": true,
        "bottom_rising": true,
        "price_date": "2026-06-29"
      },
      {
        "stock_id": "5469",
        "stock_name": "瀚宇博",
        "industry": "電子零組件業",
        "close": 89.3,
        "volume": 17912,
        "inst_buy": 11998,
        "foreign_buy": 6630,
        "trust_buy": 4492,
        "ma5": 87.02,
        "ma30": 84.44,
        "action": "買入加碼",
        "target_price": 133.95,
        "stop_loss": 80.62,
        "stop_loss_fixed": 80.37,
        "atr14": 4.34,
        "atr_pct": 4.86,
        "stop_loss_mode": "ATR",
        "first_target": 102.69,
        "sweet_buy_low": 87.23,
        "sweet_buy_high": 88.28,
        "theme_tag": "📌 其他",
        "ma10": 87.23,
        "rsi14": 66.3,
        "vol_ratio": 2.05,
        "bull_align": false,
        "chip_signal": "雙買",
        "inst_grade": "S",
        "strength_score": 98,
        "sweet_confidence": "HIGH",
        "ma5_breakout_day": 10,
        "breakout_label": "📈 趨勢延伸（第 10 日）",
        "ma5_above_ma10_days": 0,
        "trend_quality": "WEAK",
        "above_ma5_streak": 2,
        "low_guard_today": true,
        "bottom_rising": true,
        "price_date": "2026-06-29"
      },
      {
        "stock_id": "2634",
        "stock_name": "漢翔",
        "industry": "航運業",
        "close": 52.0,
        "volume": 26265,
        "inst_buy": 6980,
        "foreign_buy": 6010,
        "trust_buy": 116,
        "ma5": 49.72,
        "ma30": 47.15,
        "action": "買入加碼",
        "target_price": 78.0,
        "stop_loss": 48.84,
        "stop_loss_fixed": 46.8,
        "atr14": 1.58,
        "atr_pct": 3.04,
        "stop_loss_mode": "ATR",
        "first_target": 59.8,
        "sweet_buy_low": 49.72,
        "sweet_buy_high": 50.32,
        "theme_tag": "🚢 航運",
        "ma10": 48.71,
        "rsi14": 77.8,
        "vol_ratio": 2.54,
        "bull_align": true,
        "chip_signal": "雙買",
        "inst_grade": "S",
        "strength_score": 98,
        "sweet_confidence": "HIGH",
        "ma5_breakout_day": 9,
        "breakout_label": "📈 趨勢延伸（第 9 日）",
        "ma5_above_ma10_days": 10,
        "trend_quality": "WEAK",
        "above_ma5_streak": 1,
        "low_guard_today": true,
        "bottom_rising": false,
        "price_date": "2026-06-29"
      },
      {
        "stock_id": "2458",
        "stock_name": "義隆",
        "industry": "電子工業",
        "close": 180.0,
        "volume": 13613,
        "inst_buy": 6341,
        "foreign_buy": 4033,
        "trust_buy": 2032,
        "ma5": 172.4,
        "ma30": 161.07,
        "action": "買入加碼",
        "target_price": 270.0,
        "stop_loss": 158.78,
        "stop_loss_fixed": 162.0,
        "atr14": 10.61,
        "atr_pct": 5.89,
        "stop_loss_mode": "ATR",
        "first_target": 207.0,
        "sweet_buy_low": 171.02,
        "sweet_buy_high": 173.78,
        "theme_tag": "📌 其他",
        "ma10": 167.3,
        "rsi14": 61.9,
        "vol_ratio": 1.41,
        "bull_align": true,
        "chip_signal": "雙買",
        "inst_grade": "S",
        "strength_score": 98,
        "sweet_confidence": "MID",
        "ma5_breakout_day": 7,
        "breakout_label": "✅ 突破穩固（第 7 日）",
        "ma5_above_ma10_days": 7,
        "trend_quality": "WEAK",
        "above_ma5_streak": 1,
        "low_guard_today": true,
        "bottom_rising": false,
        "price_date": "2026-06-29"
      },
      {
        "stock_id": "2377",
        "stock_name": "微星",
        "industry": "電子工業",
        "close": 139.0,
        "volume": 23100,
        "inst_buy": 18916,
        "foreign_buy": 12704,
        "trust_buy": 10072,
        "ma5": 134.2,
        "ma30": 131.9,
        "action": "買入加碼",
        "target_price": 208.5,
        "stop_loss": 127.28,
        "stop_loss_fixed": 125.1,
        "atr14": 5.86,
        "atr_pct": 4.22,
        "stop_loss_mode": "ATR",
        "first_target": 159.85,
        "sweet_buy_low": 134.91,
        "sweet_buy_high": 137.09,
        "theme_tag": "📌 其他",
        "ma10": 136.0,
        "rsi14": 58.1,
        "vol_ratio": 1.69,
        "bull_align": false,
        "chip_signal": "雙買",
        "inst_grade": "S",
        "strength_score": 98,
        "sweet_confidence": "MID",
        "ma5_breakout_day": 29,
        "breakout_label": "📈 趨勢延伸（第 29 日）",
        "ma5_above_ma10_days": 0,
        "trend_quality": "WEAK",
        "above_ma5_streak": 1,
        "low_guard_today": true,
        "bottom_rising": true,
        "price_date": "2026-06-29"
      },
      {
        "stock_id": "6139",
        "stock_name": "亞翔",
        "industry": "電子工業",
        "close": 955.0,
        "volume": 10224,
        "inst_buy": 6952,
        "foreign_buy": 2458,
        "trust_buy": 5588,
        "ma5": 863.4,
        "ma30": 796.4,
        "action": "買入加碼",
        "target_price": 1432.5,
        "stop_loss": 839.72,
        "stop_loss_fixed": 859.5,
        "atr14": 57.64,
        "atr_pct": 6.04,
        "stop_loss_mode": "ATR",
        "first_target": 1098.25,
        "sweet_buy_low": 856.49,
        "sweet_buy_high": 870.31,
        "theme_tag": "📌 其他",
        "ma10": 845.3,
        "rsi14": 73.5,
        "vol_ratio": 1.54,
        "bull_align": true,
        "chip_signal": "雙買",
        "inst_grade": "S",
        "strength_score": 98,
        "sweet_confidence": "MID",
        "ma5_breakout_day": 29,
        "breakout_label": "📈 趨勢延伸（第 29 日）",
        "ma5_above_ma10_days": 10,
        "trend_quality": "WATCH",
        "above_ma5_streak": 4,
        "low_guard_today": true,
        "bottom_rising": true,
        "price_date": "2026-06-29"
      },
      {
        "stock_id": "4532",
        "stock_name": "瑞智",
        "industry": "電機機械",
        "close": 26.15,
        "volume": 7053,
        "inst_buy": 7315,
        "foreign_buy": 8204,
        "trust_buy": -890,
        "ma5": 24.37,
        "ma30": 24.07,
        "action": "買入加碼",
        "target_price": 39.22,
        "stop_loss": 24.58,
        "stop_loss_fixed": 23.54,
        "atr14": 0.63,
        "atr_pct": 2.41,
        "stop_loss_mode": "ATR",
        "first_target": 30.07,
        "sweet_buy_low": 24.37,
        "sweet_buy_high": 24.66,
        "theme_tag": "📌 其他",
        "ma10": 24.27,
        "rsi14": 68.6,
        "vol_ratio": 2.92,
        "bull_align": true,
        "chip_signal": "外資單買",
        "inst_grade": "S",
        "strength_score": 98,
        "sweet_confidence": "HIGH",
        "ma5_breakout_day": 24,
        "breakout_label": "📈 趨勢延伸（第 24 日）",
        "ma5_above_ma10_days": 1,
        "trend_quality": "WEAK",
        "above_ma5_streak": 1,
        "low_guard_today": true,
        "bottom_rising": false,
        "price_date": "2026-06-29"
      },
      {
        "stock_id": "4763",
        "stock_name": "材料*-KY",
        "industry": "化學生技醫療",
        "close": 47.85,
        "volume": 14719,
        "inst_buy": 6493,
        "foreign_buy": 6014,
        "trust_buy": -110,
        "ma5": 45.5,
        "ma30": 43.57,
        "action": "買入加碼",
        "target_price": 71.78,
        "stop_loss": 44.23,
        "stop_loss_fixed": 43.07,
        "atr14": 1.81,
        "atr_pct": 3.78,
        "stop_loss_mode": "ATR",
        "first_target": 55.03,
        "sweet_buy_low": 45.14,
        "sweet_buy_high": 45.86,
        "theme_tag": "💊 生技醫療",
        "ma10": 45.15,
        "rsi14": 67.2,
        "vol_ratio": 1.39,
        "bull_align": true,
        "chip_signal": "外資單買",
        "inst_grade": "S",
        "strength_score": 93,
        "sweet_confidence": "MID",
        "ma5_breakout_day": 17,
        "breakout_label": "📈 趨勢延伸（第 17 日）",
        "ma5_above_ma10_days": 17,
        "trend_quality": "WEAK",
        "above_ma5_streak": 1,
        "low_guard_today": true,
        "bottom_rising": false,
        "price_date": "2026-06-29"
      },
      {
        "stock_id": "2352",
        "stock_name": "佳世達",
        "industry": "電腦及週邊設備業",
        "close": 31.0,
        "volume": 41836,
        "inst_buy": 6544,
        "foreign_buy": -7524,
        "trust_buy": 14333,
        "ma5": 30.5,
        "ma30": 29.8,
        "action": "買入加碼",
        "target_price": 46.5,
        "stop_loss": 28.68,
        "stop_loss_fixed": 27.9,
        "atr14": 1.16,
        "atr_pct": 3.74,
        "stop_loss_mode": "ATR",
        "first_target": 35.65,
        "sweet_buy_low": 30.46,
        "sweet_buy_high": 30.96,
        "theme_tag": "📌 其他",
        "ma10": 30.71,
        "rsi14": 55.2,
        "vol_ratio": 2.6,
        "bull_align": false,
        "chip_signal": "投信單買",
        "inst_grade": "S",
        "strength_score": 93,
        "sweet_confidence": "MID",
        "ma5_breakout_day": 29,
        "breakout_label": "📈 趨勢延伸（第 29 日）",
        "ma5_above_ma10_days": 0,
        "trend_quality": "WEAK",
        "above_ma5_streak": 1,
        "low_guard_today": true,
        "bottom_rising": false,
        "price_date": "2026-06-29"
      },
      {
        "stock_id": "2404",
        "stock_name": "漢唐",
        "industry": "電子工業",
        "close": 1360.0,
        "volume": 4703,
        "inst_buy": 12294,
        "foreign_buy": 18108,
        "trust_buy": -5492,
        "ma5": 1316.0,
        "ma30": 1209.17,
        "action": "買入加碼",
        "target_price": 2040.0,
        "stop_loss": 1185.0,
        "stop_loss_fixed": 1224.0,
        "atr14": 87.5,
        "atr_pct": 6.43,
        "stop_loss_mode": "ATR",
        "first_target": 1564.0,
        "sweet_buy_low": 1305.47,
        "sweet_buy_high": 1326.53,
        "theme_tag": "📌 其他",
        "ma10": 1303.0,
        "rsi14": 67.1,
        "vol_ratio": 1.27,
        "bull_align": true,
        "chip_signal": "外資單買",
        "inst_grade": "S",
        "strength_score": 92,
        "sweet_confidence": "MID",
        "ma5_breakout_day": 29,
        "breakout_label": "📈 趨勢延伸（第 29 日）",
        "ma5_above_ma10_days": 11,
        "trend_quality": "WATCH",
        "above_ma5_streak": 3,
        "low_guard_today": true,
        "bottom_rising": true,
        "price_date": "2026-06-29"
      },
      {
        "stock_id": "2472",
        "stock_name": "立隆電",
        "industry": "電子零組件業",
        "close": 412.5,
        "volume": 17271,
        "inst_buy": 3330,
        "foreign_buy": -3403,
        "trust_buy": 6516,
        "ma5": 381.9,
        "ma30": 344.37,
        "action": "買入加碼",
        "target_price": 618.75,
        "stop_loss": 350.62,
        "stop_loss_fixed": 371.25,
        "atr14": 38.21,
        "atr_pct": 9.26,
        "stop_loss_mode": "ATR",
        "first_target": 474.37,
        "sweet_buy_low": 378.84,
        "sweet_buy_high": 384.96,
        "theme_tag": "📌 其他",
        "ma10": 380.4,
        "rsi14": 60.5,
        "vol_ratio": 1.34,
        "bull_align": true,
        "chip_signal": "投信單買",
        "inst_grade": "A",
        "strength_score": 91,
        "sweet_confidence": "MID",
        "ma5_breakout_day": 29,
        "breakout_label": "📈 趨勢延伸（第 29 日）",
        "ma5_above_ma10_days": 10,
        "trend_quality": "WEAK",
        "above_ma5_streak": 1,
        "low_guard_today": false,
        "bottom_rising": false,
        "price_date": "2026-06-29"
      },
      {
        "stock_id": "9914",
        "stock_name": "美利達",
        "industry": "運動休閒",
        "close": 78.0,
        "volume": 6791,
        "inst_buy": 7181,
        "foreign_buy": 7021,
        "trust_buy": -5,
        "ma5": 73.6,
        "ma30": 70.24,
        "action": "買入加碼",
        "target_price": 117.0,
        "stop_loss": 71.82,
        "stop_loss_fixed": 70.2,
        "atr14": 3.09,
        "atr_pct": 3.96,
        "stop_loss_mode": "ATR",
        "first_target": 89.7,
        "sweet_buy_low": 73.6,
        "sweet_buy_high": 74.48,
        "theme_tag": "📌 其他",
        "ma10": 73.43,
        "rsi14": 77.2,
        "vol_ratio": 2.89,
        "bull_align": true,
        "chip_signal": "外資單買",
        "inst_grade": "S",
        "strength_score": 91,
        "sweet_confidence": "HIGH",
        "ma5_breakout_day": 29,
        "breakout_label": "📈 趨勢延伸（第 29 日）",
        "ma5_above_ma10_days": 1,
        "trend_quality": "WATCH",
        "above_ma5_streak": 3,
        "low_guard_today": true,
        "bottom_rising": true,
        "price_date": "2026-06-29"
      },
      {
        "stock_id": "5371",
        "stock_name": "中光電",
        "industry": "光電業",
        "close": 79.0,
        "volume": 15698,
        "inst_buy": 6226,
        "foreign_buy": 5923,
        "trust_buy": -2403,
        "ma5": 76.14,
        "ma30": 71.72,
        "action": "買入加碼",
        "target_price": 118.5,
        "stop_loss": 71.64,
        "stop_loss_fixed": 71.1,
        "atr14": 3.68,
        "atr_pct": 4.66,
        "stop_loss_mode": "ATR",
        "first_target": 90.85,
        "sweet_buy_low": 75.53,
        "sweet_buy_high": 76.75,
        "theme_tag": "📺 面板/光電",
        "ma10": 73.02,
        "rsi14": 63.5,
        "vol_ratio": 1.33,
        "bull_align": true,
        "chip_signal": "外資單買",
        "inst_grade": "S",
        "strength_score": 90,
        "sweet_confidence": "MID",
        "ma5_breakout_day": 5,
        "breakout_label": "✅ 突破穩固（第 5 日）",
        "ma5_above_ma10_days": 6,
        "trend_quality": "WEAK",
        "above_ma5_streak": 1,
        "low_guard_today": true,
        "bottom_rising": false,
        "price_date": "2026-06-29"
      },
      {
        "stock_id": "3717",
        "stock_name": "聯嘉投控",
        "industry": "汽車工業",
        "close": 25.95,
        "volume": 20829,
        "inst_buy": 9811,
        "foreign_buy": 9964,
        "trust_buy": 0,
        "ma5": 23.3,
        "ma30": 22.35,
        "action": "買入加碼",
        "target_price": 38.92,
        "stop_loss": 23.33,
        "stop_loss_fixed": 23.36,
        "atr14": 1.31,
        "atr_pct": 5.05,
        "stop_loss_mode": "ATR",
        "first_target": 29.84,
        "sweet_buy_low": 23.3,
        "sweet_buy_high": 23.58,
        "theme_tag": "📌 其他",
        "ma10": 22.76,
        "rsi14": 74.2,
        "vol_ratio": 2.66,
        "bull_align": true,
        "chip_signal": "外資單買",
        "inst_grade": "S",
        "strength_score": 90,
        "sweet_confidence": "HIGH",
        "ma5_breakout_day": 5,
        "breakout_label": "✅ 突破穩固（第 5 日）",
        "ma5_above_ma10_days": 7,
        "trend_quality": "WATCH",
        "above_ma5_streak": 4,
        "low_guard_today": true,
        "bottom_rising": true,
        "price_date": "2026-06-29"
      },
      {
        "stock_id": "6691",
        "stock_name": "洋基工程",
        "industry": "其他電子業",
        "close": 795.0,
        "volume": 2334,
        "inst_buy": 3701,
        "foreign_buy": 2699,
        "trust_buy": 865,
        "ma5": 771.0,
        "ma30": 675.4,
        "action": "買入加碼",
        "target_price": 1192.5,
        "stop_loss": 708.86,
        "stop_loss_fixed": 715.5,
        "atr14": 43.07,
        "atr_pct": 5.42,
        "stop_loss_mode": "ATR",
        "first_target": 914.25,
        "sweet_buy_low": 764.83,
        "sweet_buy_high": 777.17,
        "theme_tag": "📌 其他",
        "ma10": 747.3,
        "rsi14": 76.5,
        "vol_ratio": 1.55,
        "bull_align": true,
        "chip_signal": "雙買",
        "inst_grade": "A",
        "strength_score": 87,
        "sweet_confidence": "MID",
        "ma5_breakout_day": 11,
        "breakout_label": "📈 趨勢延伸（第 11 日）",
        "ma5_above_ma10_days": 10,
        "trend_quality": "WATCH",
        "above_ma5_streak": 4,
        "low_guard_today": true,
        "bottom_rising": true,
        "price_date": "2026-06-29"
      },
      {
        "stock_id": "5328",
        "stock_name": "華容",
        "industry": "電子零組件業",
        "close": 64.7,
        "volume": 78499,
        "inst_buy": 9345,
        "foreign_buy": 8705,
        "trust_buy": 0,
        "ma5": 61.96,
        "ma30": 44.05,
        "action": "買入加碼",
        "target_price": 97.05,
        "stop_loss": 54.99,
        "stop_loss_fixed": 58.23,
        "atr14": 5.43,
        "atr_pct": 8.39,
        "stop_loss_mode": "ATR",
        "first_target": 74.41,
        "sweet_buy_low": 61.46,
        "sweet_buy_high": 62.46,
        "theme_tag": "📌 其他",
        "ma10": 57.34,
        "rsi14": 74.8,
        "vol_ratio": 1.93,
        "bull_align": true,
        "chip_signal": "外資單買",
        "inst_grade": "S",
        "strength_score": 87,
        "sweet_confidence": "MID",
        "ma5_breakout_day": 29,
        "breakout_label": "📈 趨勢延伸（第 29 日）",
        "ma5_above_ma10_days": 29,
        "trend_quality": "WEAK",
        "above_ma5_streak": 4,
        "low_guard_today": false,
        "bottom_rising": false,
        "price_date": "2026-06-29"
      },
      {
        "stock_id": "3227",
        "stock_name": "原相",
        "industry": "半導體業",
        "close": 233.5,
        "volume": 5839,
        "inst_buy": 4298,
        "foreign_buy": 2605,
        "trust_buy": 2085,
        "ma5": 226.0,
        "ma30": 224.42,
        "action": "買入加碼",
        "target_price": 350.25,
        "stop_loss": 214.86,
        "stop_loss_fixed": 210.15,
        "atr14": 9.32,
        "atr_pct": 3.99,
        "stop_loss_mode": "ATR",
        "first_target": 268.52,
        "sweet_buy_low": 224.19,
        "sweet_buy_high": 227.81,
        "theme_tag": "🔬 半導體",
        "ma10": 223.4,
        "rsi14": 65.1,
        "vol_ratio": 1.73,
        "bull_align": false,
        "chip_signal": "雙買",
        "inst_grade": "A",
        "strength_score": 86,
        "sweet_confidence": "MID",
        "ma5_breakout_day": 4,
        "breakout_label": "✅ 突破穩固（第 4 日）",
        "ma5_above_ma10_days": 7,
        "trend_quality": "WEAK",
        "above_ma5_streak": 1,
        "low_guard_today": true,
        "bottom_rising": false,
        "price_date": "2026-06-29"
      },
      {
        "stock_id": "3023",
        "stock_name": "信邦",
        "industry": "電子工業",
        "close": 325.0,
        "volume": 4207,
        "inst_buy": 4802,
        "foreign_buy": 2581,
        "trust_buy": 1969,
        "ma5": 317.4,
        "ma30": 315.2,
        "action": "買入加碼",
        "target_price": 487.5,
        "stop_loss": 295.72,
        "stop_loss_fixed": 292.5,
        "atr14": 14.64,
        "atr_pct": 4.5,
        "stop_loss_mode": "ATR",
        "first_target": 373.75,
        "sweet_buy_low": 316.7,
        "sweet_buy_high": 321.8,
        "theme_tag": "📌 其他",
        "ma10": 319.25,
        "rsi14": 50.9,
        "vol_ratio": 1.96,
        "bull_align": false,
        "chip_signal": "雙買",
        "inst_grade": "A",
        "strength_score": 86,
        "sweet_confidence": "MID",
        "ma5_breakout_day": 29,
        "breakout_label": "📈 趨勢延伸（第 29 日）",
        "ma5_above_ma10_days": 0,
        "trend_quality": "WEAK",
        "above_ma5_streak": 1,
        "low_guard_today": true,
        "bottom_rising": false,
        "price_date": "2026-06-29"
      },
      {
        "stock_id": "5230",
        "stock_name": "雷笛克光學",
        "industry": "光電業",
        "close": 22.2,
        "volume": 6207,
        "inst_buy": 823,
        "foreign_buy": 799,
        "trust_buy": 0,
        "ma5": 21.59,
        "ma30": 18.26,
        "action": "買入加碼",
        "target_price": 33.3,
        "stop_loss": 19.38,
        "stop_loss_fixed": 19.98,
        "atr14": 1.41,
        "atr_pct": 6.35,
        "stop_loss_mode": "ATR",
        "first_target": 25.53,
        "sweet_buy_low": 21.42,
        "sweet_buy_high": 21.76,
        "theme_tag": "📺 面板/光電",
        "ma10": 20.79,
        "rsi14": 67.3,
        "vol_ratio": 1.86,
        "bull_align": true,
        "chip_signal": "外資單買",
        "inst_grade": "B",
        "strength_score": 85,
        "sweet_confidence": "MID",
        "ma5_breakout_day": 19,
        "breakout_label": "📈 趨勢延伸（第 19 日）",
        "ma5_above_ma10_days": 9,
        "trend_quality": "WATCH",
        "above_ma5_streak": 3,
        "low_guard_today": true,
        "bottom_rising": true,
        "price_date": "2026-06-29"
      },
      {
        "stock_id": "6472",
        "stock_name": "保瑞",
        "industry": "化學生技醫療",
        "close": 437.5,
        "volume": 3018,
        "inst_buy": 3776,
        "foreign_buy": 3848,
        "trust_buy": -56,
        "ma5": 430.4,
        "ma30": 387.6,
        "action": "買入加碼",
        "target_price": 656.25,
        "stop_loss": 395.5,
        "stop_loss_fixed": 393.75,
        "atr14": 21.0,
        "atr_pct": 4.8,
        "stop_loss_mode": "ATR",
        "first_target": 503.12,
        "sweet_buy_low": 426.96,
        "sweet_buy_high": 433.84,
        "theme_tag": "💊 生技醫療",
        "ma10": 422.55,
        "rsi14": 65.0,
        "vol_ratio": 1.68,
        "bull_align": true,
        "chip_signal": "外資單買",
        "inst_grade": "A",
        "strength_score": 85,
        "sweet_confidence": "HIGH",
        "ma5_breakout_day": 13,
        "breakout_label": "📈 趨勢延伸（第 13 日）",
        "ma5_above_ma10_days": 16,
        "trend_quality": "WEAK",
        "above_ma5_streak": 1,
        "low_guard_today": true,
        "bottom_rising": false,
        "price_date": "2026-06-29"
      },
      {
        "stock_id": "1444",
        "stock_name": "力麗",
        "industry": "紡織纖維",
        "close": 8.15,
        "volume": 13354,
        "inst_buy": 4145,
        "foreign_buy": 3852,
        "trust_buy": 0,
        "ma5": 7.27,
        "ma30": 6.71,
        "action": "買入加碼",
        "target_price": 12.23,
        "stop_loss": 7.61,
        "stop_loss_fixed": 7.34,
        "atr14": 0.27,
        "atr_pct": 3.31,
        "stop_loss_mode": "ATR",
        "first_target": 9.37,
        "sweet_buy_low": 7.27,
        "sweet_buy_high": 7.36,
        "theme_tag": "📌 其他",
        "ma10": 7.17,
        "rsi14": 71.8,
        "vol_ratio": 2.93,
        "bull_align": true,
        "chip_signal": "外資單買",
        "inst_grade": "A",
        "strength_score": 85,
        "sweet_confidence": "HIGH",
        "ma5_breakout_day": 20,
        "breakout_label": "📈 趨勢延伸（第 20 日）",
        "ma5_above_ma10_days": 1,
        "trend_quality": "WEAK",
        "above_ma5_streak": 2,
        "low_guard_today": true,
        "bottom_rising": true,
        "price_date": "2026-06-29"
      },
      {
        "stock_id": "3605",
        "stock_name": "宏致",
        "industry": "電子零組件業",
        "close": 78.0,
        "volume": 4647,
        "inst_buy": 2874,
        "foreign_buy": 3176,
        "trust_buy": 0,
        "ma5": 77.02,
        "ma30": 76.91,
        "action": "買入加碼",
        "target_price": 117.0,
        "stop_loss": 69.88,
        "stop_loss_fixed": 70.2,
        "atr14": 4.06,
        "atr_pct": 5.21,
        "stop_loss_mode": "ATR",
        "first_target": 89.7,
        "sweet_buy_low": 76.4,
        "sweet_buy_high": 77.64,
        "theme_tag": "📌 其他",
        "ma10": 76.94,
        "rsi14": 58.8,
        "vol_ratio": 1.74,
        "bull_align": true,
        "chip_signal": "外資單買",
        "inst_grade": "A",
        "strength_score": 82,
        "sweet_confidence": "HIGH",
        "ma5_breakout_day": 5,
        "breakout_label": "✅ 突破穩固（第 5 日）",
        "ma5_above_ma10_days": 8,
        "trend_quality": "WEAK",
        "above_ma5_streak": 1,
        "low_guard_today": true,
        "bottom_rising": false,
        "price_date": "2026-06-29"
      },
      {
        "stock_id": "1210",
        "stock_name": "大成",
        "industry": "食品工業",
        "close": 55.2,
        "volume": 3530,
        "inst_buy": 12711,
        "foreign_buy": -35320,
        "trust_buy": 47362,
        "ma5": 55.1,
        "ma30": 53.96,
        "action": "買入加碼",
        "target_price": 82.8,
        "stop_loss": 51.89,
        "stop_loss_fixed": 49.68,
        "atr14": 1.0,
        "atr_pct": 1.81,
        "stop_loss_mode": "ATR",
        "first_target": 63.48,
        "sweet_buy_low": 54.7,
        "sweet_buy_high": 55.58,
        "theme_tag": "📌 其他",
        "ma10": 55.14,
        "rsi14": 61.1,
        "vol_ratio": 1.36,
        "bull_align": false,
        "chip_signal": "投信單買",
        "inst_grade": "S",
        "strength_score": 82,
        "sweet_confidence": "MID",
        "ma5_breakout_day": 17,
        "breakout_label": "📈 趨勢延伸（第 17 日）",
        "ma5_above_ma10_days": 0,
        "trend_quality": "WATCH",
        "above_ma5_streak": 4,
        "low_guard_today": true,
        "bottom_rising": true,
        "price_date": "2026-06-29"
      },
      {
        "stock_id": "2887",
        "stock_name": "台新新光金",
        "industry": "金融保險",
        "close": 33.0,
        "volume": 84407,
        "inst_buy": 603735,
        "foreign_buy": 11045,
        "trust_buy": 608717,
        "ma5": 32.1,
        "ma30": 27.93,
        "action": "買入加碼",
        "target_price": 49.5,
        "stop_loss": 30.6,
        "stop_loss_fixed": 29.7,
        "atr14": 1.2,
        "atr_pct": 3.64,
        "stop_loss_mode": "ATR",
        "first_target": 37.95,
        "sweet_buy_low": 31.89,
        "sweet_buy_high": 32.41,
        "theme_tag": "🏦 金融",
        "ma10": 32.15,
        "rsi14": 79.0,
        "vol_ratio": 1.33,
        "bull_align": false,
        "chip_signal": "雙買",
        "inst_grade": "S",
        "strength_score": 81,
        "sweet_confidence": "MID",
        "ma5_breakout_day": 19,
        "breakout_label": "📈 趨勢延伸（第 19 日）",
        "ma5_above_ma10_days": 0,
        "trend_quality": "WEAK",
        "above_ma5_streak": 1,
        "low_guard_today": true,
        "bottom_rising": false,
        "price_date": "2026-06-29"
      },
      {
        "stock_id": "5434",
        "stock_name": "崇越",
        "industry": "電子通路業",
        "close": 539.0,
        "volume": 3510,
        "inst_buy": 3148,
        "foreign_buy": 3301,
        "trust_buy": -191,
        "ma5": 502.9,
        "ma30": 463.08,
        "action": "買入加碼",
        "target_price": 808.5,
        "stop_loss": 494.22,
        "stop_loss_fixed": 485.1,
        "atr14": 22.39,
        "atr_pct": 4.15,
        "stop_loss_mode": "ATR",
        "first_target": 619.85,
        "sweet_buy_low": 502.9,
        "sweet_buy_high": 508.93,
        "theme_tag": "📌 其他",
        "ma10": 491.25,
        "rsi14": 77.7,
        "vol_ratio": 2.06,
        "bull_align": true,
        "chip_signal": "外資單買",
        "inst_grade": "A",
        "strength_score": 81,
        "sweet_confidence": "HIGH",
        "ma5_breakout_day": 25,
        "breakout_label": "📈 趨勢延伸（第 25 日）",
        "ma5_above_ma10_days": 9,
        "trend_quality": "WEAK",
        "above_ma5_streak": 1,
        "low_guard_today": true,
        "bottom_rising": true,
        "price_date": "2026-06-29"
      },
      {
        "stock_id": "2903",
        "stock_name": "遠百",
        "industry": "貿易百貨",
        "close": 23.45,
        "volume": 6291,
        "inst_buy": 2634,
        "foreign_buy": -4651,
        "trust_buy": 6866,
        "ma5": 23.31,
        "ma30": 22.87,
        "action": "買入加碼",
        "target_price": 35.17,
        "stop_loss": 22.04,
        "stop_loss_fixed": 21.11,
        "atr14": 0.49,
        "atr_pct": 2.09,
        "stop_loss_mode": "ATR",
        "first_target": 26.97,
        "sweet_buy_low": 23.43,
        "sweet_buy_high": 23.81,
        "theme_tag": "📌 其他",
        "ma10": 23.62,
        "rsi14": 59.4,
        "vol_ratio": 1.67,
        "bull_align": false,
        "chip_signal": "投信單買",
        "inst_grade": "A",
        "strength_score": 80,
        "sweet_confidence": "MID",
        "ma5_breakout_day": 17,
        "breakout_label": "📈 趨勢延伸（第 17 日）",
        "ma5_above_ma10_days": 0,
        "trend_quality": "WEAK",
        "above_ma5_streak": 1,
        "low_guard_today": true,
        "bottom_rising": false,
        "price_date": "2026-06-29"
      },
      {
        "stock_id": "4541",
        "stock_name": "晟田",
        "industry": "其他",
        "close": 48.65,
        "volume": 2335,
        "inst_buy": 2488,
        "foreign_buy": 2524,
        "trust_buy": 0,
        "ma5": 48.31,
        "ma30": 46.72,
        "action": "買入加碼",
        "target_price": 72.97,
        "stop_loss": 44.75,
        "stop_loss_fixed": 43.78,
        "atr14": 1.95,
        "atr_pct": 4.01,
        "stop_loss_mode": "ATR",
        "first_target": 55.95,
        "sweet_buy_low": 48.76,
        "sweet_buy_high": 49.54,
        "theme_tag": "📌 其他",
        "ma10": 49.15,
        "rsi14": 58.5,
        "vol_ratio": 1.96,
        "bull_align": false,
        "chip_signal": "外資單買",
        "inst_grade": "A",
        "strength_score": 73,
        "sweet_confidence": "MID",
        "ma5_breakout_day": 17,
        "breakout_label": "📈 趨勢延伸（第 17 日）",
        "ma5_above_ma10_days": 0,
        "trend_quality": "WEAK",
        "above_ma5_streak": 1,
        "low_guard_today": true,
        "bottom_rising": false,
        "price_date": "2026-06-29"
      },
      {
        "stock_id": "2425",
        "stock_name": "承啟",
        "industry": "電腦及週邊設備業",
        "close": 41.1,
        "volume": 7211,
        "inst_buy": 56,
        "foreign_buy": 55,
        "trust_buy": 0,
        "ma5": 40.15,
        "ma30": 36.56,
        "action": "買入加碼",
        "target_price": 61.65,
        "stop_loss": 35.42,
        "stop_loss_fixed": 36.99,
        "atr14": 2.84,
        "atr_pct": 6.91,
        "stop_loss_mode": "ATR",
        "first_target": 47.27,
        "sweet_buy_low": 39.83,
        "sweet_buy_high": 40.47,
        "theme_tag": "📌 其他",
        "ma10": 39.86,
        "rsi14": 67.6,
        "vol_ratio": 1.46,
        "bull_align": true,
        "chip_signal": "外資單買",
        "inst_grade": "C",
        "strength_score": 73,
        "sweet_confidence": "MID",
        "ma5_breakout_day": 29,
        "breakout_label": "📈 趨勢延伸（第 29 日）",
        "ma5_above_ma10_days": 10,
        "trend_quality": "WEAK",
        "above_ma5_streak": 1,
        "low_guard_today": true,
        "bottom_rising": true,
        "price_date": "2026-06-29"
      },
      {
        "stock_id": "8183",
        "stock_name": "精星",
        "industry": "其他電子類",
        "close": 34.1,
        "volume": 2597,
        "inst_buy": 236,
        "foreign_buy": 179,
        "trust_buy": 0,
        "ma5": 32.56,
        "ma30": 31.97,
        "action": "買入加碼",
        "target_price": 51.15,
        "stop_loss": 31.46,
        "stop_loss_fixed": 30.69,
        "atr14": 1.32,
        "atr_pct": 3.87,
        "stop_loss_mode": "ATR",
        "first_target": 39.21,
        "sweet_buy_low": 32.44,
        "sweet_buy_high": 32.96,
        "theme_tag": "📌 其他",
        "ma10": 32.7,
        "rsi14": 64.7,
        "vol_ratio": 2.72,
        "bull_align": false,
        "chip_signal": "外資單買",
        "inst_grade": "C",
        "strength_score": 72,
        "sweet_confidence": "MID",
        "ma5_breakout_day": 8,
        "breakout_label": "📈 趨勢延伸（第 8 日）",
        "ma5_above_ma10_days": 0,
        "trend_quality": "WEAK",
        "above_ma5_streak": 1,
        "low_guard_today": true,
        "bottom_rising": true,
        "price_date": "2026-06-29"
      },
      {
        "stock_id": "5269",
        "stock_name": "祥碩",
        "industry": "半導體業",
        "close": 1475.0,
        "volume": 2003,
        "inst_buy": 1125,
        "foreign_buy": -70,
        "trust_buy": 1264,
        "ma5": 1425.0,
        "ma30": 1446.33,
        "action": "買入加碼",
        "target_price": 2212.5,
        "stop_loss": 1344.28,
        "stop_loss_fixed": 1327.5,
        "atr14": 65.36,
        "atr_pct": 4.43,
        "stop_loss_mode": "ATR",
        "first_target": 1696.25,
        "sweet_buy_low": 1413.6,
        "sweet_buy_high": 1436.4,
        "theme_tag": "🔬 半導體",
        "ma10": 1421.5,
        "rsi14": 57.4,
        "vol_ratio": 2.05,
        "bull_align": false,
        "chip_signal": "投信單買",
        "inst_grade": "A",
        "strength_score": 72,
        "sweet_confidence": "MID",
        "ma5_breakout_day": 0,
        "breakout_label": "",
        "ma5_above_ma10_days": 6,
        "trend_quality": "WEAK",
        "above_ma5_streak": 1,
        "low_guard_today": true,
        "bottom_rising": false,
        "price_date": "2026-06-29"
      },
      {
        "stock_id": "2406",
        "stock_name": "國碩",
        "industry": "電子工業",
        "close": 38.0,
        "volume": 21060,
        "inst_buy": 201,
        "foreign_buy": 39,
        "trust_buy": 0,
        "ma5": 35.23,
        "ma30": 34.92,
        "action": "買入加碼",
        "target_price": 57.0,
        "stop_loss": 32.3,
        "stop_loss_fixed": 34.2,
        "atr14": 2.86,
        "atr_pct": 7.53,
        "stop_loss_mode": "ATR",
        "first_target": 43.7,
        "sweet_buy_low": 35.34,
        "sweet_buy_high": 35.9,
        "theme_tag": "📌 其他",
        "ma10": 35.62,
        "rsi14": 63.3,
        "vol_ratio": 1.39,
        "bull_align": false,
        "chip_signal": "外資單買",
        "inst_grade": "C",
        "strength_score": 71,
        "sweet_confidence": "MID",
        "ma5_breakout_day": 23,
        "breakout_label": "📈 趨勢延伸（第 23 日）",
        "ma5_above_ma10_days": 0,
        "trend_quality": "WEAK",
        "above_ma5_streak": 1,
        "low_guard_today": true,
        "bottom_rising": true,
        "price_date": "2026-06-29"
      },
      {
        "stock_id": "9921",
        "stock_name": "巨大",
        "industry": "運動休閒",
        "close": 77.1,
        "volume": 3135,
        "inst_buy": 83,
        "foreign_buy": 91,
        "trust_buy": 178,
        "ma5": 75.08,
        "ma30": 72.21,
        "action": "買入加碼",
        "target_price": 115.65,
        "stop_loss": 71.58,
        "stop_loss_fixed": 69.39,
        "atr14": 2.76,
        "atr_pct": 3.58,
        "stop_loss_mode": "ATR",
        "first_target": 88.66,
        "sweet_buy_low": 74.71,
        "sweet_buy_high": 75.91,
        "theme_tag": "📌 其他",
        "ma10": 75.31,
        "rsi14": 70.2,
        "vol_ratio": 1.85,
        "bull_align": false,
        "chip_signal": "雙買",
        "inst_grade": "C",
        "strength_score": 69,
        "sweet_confidence": "MID",
        "ma5_breakout_day": 17,
        "breakout_label": "📈 趨勢延伸（第 17 日）",
        "ma5_above_ma10_days": 0,
        "trend_quality": "WATCH",
        "above_ma5_streak": 3,
        "low_guard_today": true,
        "bottom_rising": true,
        "price_date": "2026-06-29"
      },
      {
        "stock_id": "6156",
        "stock_name": "松上",
        "industry": "電子零組件業",
        "close": 26.25,
        "volume": 6670,
        "inst_buy": 831,
        "foreign_buy": 755,
        "trust_buy": 0,
        "ma5": 25.49,
        "ma30": 20.95,
        "action": "買入加碼",
        "target_price": 39.38,
        "stop_loss": 22.61,
        "stop_loss_fixed": 23.62,
        "atr14": 1.82,
        "atr_pct": 6.93,
        "stop_loss_mode": "ATR",
        "first_target": 30.19,
        "sweet_buy_low": 25.29,
        "sweet_buy_high": 25.69,
        "theme_tag": "📌 其他",
        "ma10": 24.74,
        "rsi14": 77.9,
        "vol_ratio": 1.35,
        "bull_align": true,
        "chip_signal": "外資單買",
        "inst_grade": "B",
        "strength_score": 68,
        "sweet_confidence": "MID",
        "ma5_breakout_day": 11,
        "breakout_label": "📈 趨勢延伸（第 11 日）",
        "ma5_above_ma10_days": 11,
        "trend_quality": "WEAK",
        "above_ma5_streak": 1,
        "low_guard_today": true,
        "bottom_rising": true,
        "price_date": "2026-06-29"
      },
      {
        "stock_id": "6259",
        "stock_name": "百徽",
        "industry": "電子零組件業",
        "close": 37.8,
        "volume": 2864,
        "inst_buy": 470,
        "foreign_buy": 492,
        "trust_buy": 0,
        "ma5": 37.75,
        "ma30": 29.41,
        "action": "買入加碼",
        "target_price": 56.7,
        "stop_loss": 32.13,
        "stop_loss_fixed": 34.02,
        "atr14": 3.14,
        "atr_pct": 8.31,
        "stop_loss_mode": "ATR",
        "first_target": 43.47,
        "sweet_buy_low": 37.45,
        "sweet_buy_high": 38.05,
        "theme_tag": "📌 其他",
        "ma10": 35.87,
        "rsi14": 68.1,
        "vol_ratio": 1.36,
        "bull_align": true,
        "chip_signal": "外資單買",
        "inst_grade": "C",
        "strength_score": 66,
        "sweet_confidence": "MID",
        "ma5_breakout_day": 29,
        "breakout_label": "📈 趨勢延伸（第 29 日）",
        "ma5_above_ma10_days": 12,
        "trend_quality": "WEAK",
        "above_ma5_streak": 3,
        "low_guard_today": false,
        "bottom_rising": false,
        "price_date": "2026-06-29"
      },
      {
        "stock_id": "8227",
        "stock_name": "巨有科技",
        "industry": "半導體業",
        "close": 205.5,
        "volume": 3043,
        "inst_buy": 195,
        "foreign_buy": 619,
        "trust_buy": -196,
        "ma5": 188.92,
        "ma30": 197.94,
        "action": "買入加碼",
        "target_price": 308.25,
        "stop_loss": 178.82,
        "stop_loss_fixed": 184.95,
        "atr14": 13.34,
        "atr_pct": 6.49,
        "stop_loss_mode": "ATR",
        "first_target": 236.32,
        "sweet_buy_low": 187.41,
        "sweet_buy_high": 190.43,
        "theme_tag": "🔬 半導體",
        "ma10": 185.73,
        "rsi14": 59.9,
        "vol_ratio": 1.68,
        "bull_align": false,
        "chip_signal": "外資單買",
        "inst_grade": "C",
        "strength_score": 58,
        "sweet_confidence": "MID",
        "ma5_breakout_day": 0,
        "breakout_label": "",
        "ma5_above_ma10_days": 6,
        "trend_quality": "WEAK",
        "above_ma5_streak": 2,
        "low_guard_today": true,
        "bottom_rising": false,
        "price_date": "2026-06-29"
      }
    ]
  }
}